{"timeData":[{"timestamp":1575936000000,"creationCount":70,"tokenCreationCount":0,"txCount":24680,"growthCount":2732,"reward":6859542.578561636,"staked":"0","buffer":null,"tokens":null,"networkVolumeRune":null,"networkVolumeUSD":null},{"timestamp":1578528000000,"creationCount":1981,"tokenCreationCount":0,"txCount":388411,"growthCount":45623,"reward":125021811.49703136,"staked":"0","buffer":null,"tokens":null,"networkVolumeRune":null,"networkVolumeUSD":null},{"timestamp":1581120000000,"creationCount":788,"tokenCreationCount":0,"txCount":410834,"growthCount":46367,"reward":120787831.44218709,"staked":"0","buffer":null,"tokens":null,"networkVolumeRune":null,"networkVolumeUSD":null},{"timestamp":1583712000000,"creationCount":474,"tokenCreationCount":0,"txCount":416137,"growthCount":45707,"reward":117618150.15151376,"staked":"0","buffer":null,"tokens":null,"networkVolumeRune":null,"networkVolumeUSD":null},{"timestamp":1586304000000,"creationCount":2027,"tokenCreationCount":0,"txCount":472704,"growthCount":46562,"reward":115295928.90619454,"staked":"0","buffer":null,"tokens":null,"networkVolumeRune":null,"networkVolumeUSD":null},{"timestamp":1588896000000,"creationCount":1204,"tokenCreationCount":1,"txCount":756713,"growthCount":67394,"reward":103082249.50198054,"staked":"0","buffer":null,"tokens":null,"networkVolumeRune":null,"networkVolumeUSD":null},{"timestamp":1591488000000,"creationCount":3598,"tokenCreationCount":1,"txCount":872111,"growthCount":46130,"reward":99252019.94072509,"staked":"0","buffer":null,"tokens":null,"networkVolumeRune":null,"networkVolumeUSD":null},{"timestamp":1594080000000,"creationCount":3354,"tokenCreationCount":65,"txCount":851600,"growthCount":87342,"reward":103665426.35924378,"staked":"0","buffer":null,"tokens":[{"hash":"zil1gg3twtmrfx4k7fr5psj9dc06hrjhjunw49qlyu","decimals":null,"volume":"10","symbol":"mainnet baby"},{"hash":"zil15cg62c05jchxf2ttchtm7j5q8g72n3dqumfjpr","decimals":null,"volume":"2","symbol":"mainnet baby"},{"hash":"zil1gdf3dl0pvqpdufp8cezytg7lcz3r6640d5cwrg","decimals":null,"volume":"477","symbol":"Exploring creativity and space within the same medium. Quality and rare works of art. "},{"hash":"zil17tq34p490dyvxfp65znuucr9aqd8dsy7hrmjkj","decimals":null,"volume":"1363","symbol":"Zilliqa Crypto Collectables"},{"hash":"zil1n5t6xpa4tgwkprssv0rpjr7l7pj0lw2j999rmr","decimals":null,"volume":"10","symbol":"Hello"},{"hash":"zil13zmkv6ced5rnrkvrmm8dn6jx49nkf7evevgal5","decimals":null,"volume":"1836","symbol":"Imagine the unimaginable and possess "},{"hash":"zil1datrglc3mkldte96clft6hrd5mes55xmqnkqdu","decimals":null,"volume":"20","symbol":"Mixed media artworks"},{"hash":"zil10kju3mklervptt7dve6lsg0mlj76ja3j0jle62","decimals":null,"volume":"9","symbol":"metamediary"},{"hash":"zil1scad4zzgf9d6cv8rqltuqh2tskr6hwpmx8tymg","decimals":null,"volume":"16","symbol":"BruceTheGoose"},{"hash":"zil19ktxvzrsvgn7tsmr8kgrmpmlmu4djc22f3q0vm","decimals":null,"volume":"4","symbol":"Cute NFT Collectibles"},{"hash":"zil1d45t8yrxfsu5ac0wys8jwajh5sst0eech4my7n","decimals":null,"volume":"40","symbol":"The Cryptovarium"},{"hash":"zil1r7zljxaal92k4e40wuftd6dj2t92c3qk2hwku5","decimals":null,"volume":"2","symbol":"by Greg Tjosvold"},{"hash":"zil1ch9v5whatgy974aduuc8v8ktqhurk98tdjykfs","decimals":null,"volume":"101","symbol":"All arte you will eve need"},{"hash":"zil17hua9zunnj8s3afud7y8pr536ewpv6qalcj888","decimals":null,"volume":"74","symbol":"Dream Lofty dreams, and as you dream, so you shall become. Fantasy, dream state , dream works, smile, "},{"hash":"zil1edw9jv02d55r63u2s0h2nxwnvc7mvx4pprcjt6","decimals":null,"volume":"82","symbol":"Only rare collectibles at our store"},{"hash":"zil1shfd7qwnq4dqhfydr6rqj2yvmu88ctjhjg093d","decimals":null,"volume":"18","symbol":"Periodic Table of Elements"},{"hash":"zil17wwksg2jzder2l92xehfyk92cwp3qsexw4frfz","decimals":null,"volume":"2","symbol":"Music Collectibles"},{"hash":"zil1mqyhntrz6q2lmfeqeacp2gn43a0mt3e09f6da3","decimals":null,"volume":"158","symbol":"20,000 plus zil domains to be listed"},{"hash":"zil1lf8vst6eedwm50n7h2mj324u5n6fsalenpjjh9","decimals":null,"volume":"959","symbol":"The one and only official NFT store by Zilliqa, featuring limited edition #Zilliqa NFTs"},{"hash":"zil192jt60t0uzw7twc39wuh8ewsxst008sfs75wc5","decimals":null,"volume":"4","symbol":"Art. Music. Craft. "},{"hash":"zil1xmj54v9kgq4yl2xwy56r63c5ssqufkljxhldt5","decimals":null,"volume":"20","symbol":"Blender 3D models "},{"hash":"zil14mp8zfjrnrzut8r8e5fhrhsxjekh8cuyqpm9ll","decimals":null,"volume":"2","symbol":"General use face mask"},{"hash":"zil1hac2alqcukyhaytqu8lsuyjrg7eytnlc93zcer","decimals":null,"volume":"2","symbol":"Brazil ZilPay Domain"},{"hash":"zil123480dy6prlvx6rjgjecgmum9h9jp7x0d4w7zf","decimals":null,"volume":"2","symbol":"My best photography for you"},{"hash":"zil18usfgphvpnd4n3w6a74ec8l2nngqq5395fgxn5","decimals":null,"volume":"6","symbol":"One of a kind NFT Artwork and Collectables"},{"hash":"zil1amn8fr7ugtwwd6nq44zxe0jcsnv2phyumjanu7","decimals":null,"volume":"190","symbol":"Abstract"},{"hash":"zil1q99x3dxkxrd4n6jeymsj0aw68xkxpc7upcu2ax","decimals":null,"volume":"5","symbol":"Time, Space and Reality"},{"hash":"zil1h7d9a8myxcay4cuzw07xp6grns9djxj7n89lzs","decimals":null,"volume":"30","symbol":"ZIL SWIPE TEXT - ART"},{"hash":"zil1pde0gh3seu2cpuu2ma0k4mqf9gved2722l3uu7","decimals":null,"volume":"2","symbol":"Organic Full Spectrum CBD Oil"}],"networkVolumeRune":null,"networkVolumeUSD":null},{"timestamp":1596672000000,"creationCount":4396,"tokenCreationCount":40,"txCount":794721,"growthCount":64680,"reward":103408405.91301958,"staked":"0","buffer":null,"tokens":[{"hash":"zil13zmkv6ced5rnrkvrmm8dn6jx49nkf7evevgal5","decimals":null,"volume":"3259","symbol":"Imagine the unimaginable and possess "},{"hash":"zil1lf8vst6eedwm50n7h2mj324u5n6fsalenpjjh9","decimals":null,"volume":"202","symbol":"The one and only official NFT store by Zilliqa, featuring limited edition #Zilliqa NFTs"},{"hash":"zil1wc2wnxg4pv42ly8u0g38rufldsueptquax0zgc","decimals":null,"volume":"6","symbol":"\"record now, watch later\""},{"hash":"zil1edw9jv02d55r63u2s0h2nxwnvc7mvx4pprcjt6","decimals":null,"volume":"2556","symbol":"Only rare collectibles at our store"},{"hash":"zil1mwdu67ep94gu7lya74zkga7n5egxwha09nezd8","decimals":null,"volume":"1","symbol":"This is a Random store"},{"hash":"zil1q99x3dxkxrd4n6jeymsj0aw68xkxpc7upcu2ax","decimals":null,"volume":"43","symbol":"Time, Space and Reality"},{"hash":"zil1h7d9a8myxcay4cuzw07xp6grns9djxj7n89lzs","decimals":null,"volume":"251","symbol":"ZIL SWIPE TEXT - ART"},{"hash":"zil1adxj5gsfc08q2rzn5fquxt8z5nd7zmw4a8a0xq","decimals":null,"volume":"2","symbol":"Collection of Photo's"},{"hash":"zil138umtnw6d5aps3qpuvjpp2yxlruwejef585ccz","decimals":null,"volume":"2","symbol":"my NFT rare gallery"},{"hash":"zil1ch9v5whatgy974aduuc8v8ktqhurk98tdjykfs","decimals":null,"volume":"711","symbol":"All arte you will eve need"},{"hash":"zil1shfd7qwnq4dqhfydr6rqj2yvmu88ctjhjg093d","decimals":null,"volume":"630","symbol":"Periodic Table of Elements"},{"hash":"zil1vsqxhdsl80kqdedlz4f82qjw0uu3wduev3gsxa","decimals":null,"volume":"6","symbol":"Art by LazyCryptoGuy"},{"hash":"zil1m95aem99cvywvy00r6zakp6kyd6rrkkdrtt809","decimals":null,"volume":"2","symbol":"Photography and arts"},{"hash":"zil192jt60t0uzw7twc39wuh8ewsxst008sfs75wc5","decimals":null,"volume":"27","symbol":"Art. Music. Craft. "},{"hash":"zil1scad4zzgf9d6cv8rqltuqh2tskr6hwpmx8tymg","decimals":null,"volume":"14","symbol":"BruceTheGoose"},{"hash":"zil1amn8fr7ugtwwd6nq44zxe0jcsnv2phyumjanu7","decimals":null,"volume":"991","symbol":"Abstract"},{"hash":"zil1x7jnvlpwtnhzu94v332wrn9qa766d334xjuvug","decimals":null,"volume":"69","symbol":"art and photos from me and the internet from a time that will never be forgotten. photos in the collages are put together by me from pictures on the net, mostly news photos."},{"hash":"zil1q4whlftdfa5sc8rqzeh5zz3d6twpqh222rnfqh","decimals":null,"volume":"742","symbol":"Support your favorite cryptocurrency!"},{"hash":"zil175q3lj2dnn4tv48gg8uq330qjl5tqjgajqvwdz","decimals":null,"volume":"1","symbol":"DCL & CV"},{"hash":"zil17tq34p490dyvxfp65znuucr9aqd8dsy7hrmjkj","decimals":null,"volume":"1686","symbol":"Zilliqa Crypto Collectables"},{"hash":"zil1hftuavppz8zal0qcefjlzdfv8rxvy70lvj5njq","decimals":null,"volume":"2621","symbol":"Pick yours out of the box..."},{"hash":"zil17hua9zunnj8s3afud7y8pr536ewpv6qalcj888","decimals":null,"volume":"182","symbol":"Dream Lofty dreams, and as you dream, so you shall become. Fantasy, dream state , dream works, smile, "},{"hash":"zil180v66mlw007ltdv8tq5t240y7upwgf7djklmwh","decimals":6,"volume":"260042390000","symbol":"XSGD"},{"hash":"zil1xuggstjfsrye8g64y0jvuym7w6ltphhy5785lj","decimals":null,"volume":"226","symbol":"Super rare digital collectibles showroom"},{"hash":"zil1huvwn39kshpsqzx82hckqpm2k8ecq0kz6me4ka","decimals":null,"volume":"70","symbol":"limited edition sneakers"},{"hash":"zil1mwafgec7nv6t8689sc0l37h5zjqpru7fyqnzky","decimals":null,"volume":"42","symbol":"Cute little cryptonions!"},{"hash":"zil14kw6uq3xvr9sdywzkcct6gxn6galdds3esr502","decimals":null,"volume":"2","symbol":"Special Zil Drops"},{"hash":"zil14v05mu826pugnznpx2gdp4fkkc46kxz5wspacv","decimals":null,"volume":"11","symbol":"Real pencil sketch, digital sketch, artistic graphic NFTs available"},{"hash":"zil1ljl5gxvc4hq5nvkxtuu0566kzmvsfp2haml0p2","decimals":18,"volume":"107","symbol":"AMT"},{"hash":"zil14kzm6z8ttxj3pyxveqjhdpe8snj83zr9qa8tx9","decimals":18,"volume":"1000","symbol":"YFI"},{"hash":"zil1fsv05jc592g7k6dg6gjttdrv2d4l4ecx2kzlcp","decimals":null,"volume":"6","symbol":"doteth"},{"hash":"zil1gfh80zp0xspnzp9nc9ps3v603dm5ye9h3rnyam","decimals":null,"volume":"3","symbol":"PBS"},{"hash":"zil1u5z9j380n4hfekxhe8xule3dt0xcw900lu2xa4","decimals":null,"volume":"2","symbol":"once in a lifetime moments"},{"hash":"zil1crkgcnc3ua2y7m6wvvl4dx9lex58763u96lza7","decimals":null,"volume":"21","symbol":"Converting real things to the digital assets"},{"hash":"zil10k24syejup7t7svnq8z6dsddxe38ys5n5ptehx","decimals":null,"volume":"1","symbol":"Create and sell unique item with limited supply"},{"hash":"zil1p34stlpjfyx2wewf727xhxhv6mrqw4k7zuhmp7","decimals":null,"volume":"3","symbol":"A store for big splashers."},{"hash":"zil1gp25k55se37fh2wnff2tsr3fz3uz0fun2wjcmv","decimals":null,"volume":"12","symbol":"VibeGuru.zil Tokens"}],"networkVolumeRune":null,"networkVolumeUSD":null},{"timestamp":1599264000000,"creationCount":4977,"tokenCreationCount":30,"txCount":831862,"growthCount":81851,"reward":99267033.1144957,"staked":"0","buffer":null,"tokens":[{"hash":"zil1edw9jv02d55r63u2s0h2nxwnvc7mvx4pprcjt6","decimals":null,"volume":"357","symbol":"Only rare collectibles at our store"},{"hash":"zil1shfd7qwnq4dqhfydr6rqj2yvmu88ctjhjg093d","decimals":null,"volume":"2722","symbol":"Periodic Table of Elements"},{"hash":"zil1j4gm73fnwvdy8cf37kx08vvdkwxun2yjyr0ems","decimals":null,"volume":"55","symbol":"PHX"},{"hash":"zil1qh9w6ye62xnt6uldk6wqp4qkq94m56v7pljy5f","decimals":null,"volume":"2","symbol":"Artwork and Collections"},{"hash":"zil17hua9zunnj8s3afud7y8pr536ewpv6qalcj888","decimals":null,"volume":"168","symbol":"Dream Lofty dreams, and as you dream, so you shall become. Fantasy, dream state , dream works, smile, "},{"hash":"zil180v66mlw007ltdv8tq5t240y7upwgf7djklmwh","decimals":6,"volume":"410120650128","symbol":"XSGD"},{"hash":"zil13zmkv6ced5rnrkvrmm8dn6jx49nkf7evevgal5","decimals":null,"volume":"434","symbol":"Imagine the unimaginable and possess "},{"hash":"zil1lf8vst6eedwm50n7h2mj324u5n6fsalenpjjh9","decimals":null,"volume":"62","symbol":"The one and only official NFT store by Zilliqa, featuring limited edition #Zilliqa NFTs"},{"hash":"zil17tq34p490dyvxfp65znuucr9aqd8dsy7hrmjkj","decimals":null,"volume":"15","symbol":"Zilliqa Crypto Collectables"},{"hash":"zil1kkjzy0m33psgglkf6wcxgxfxdd6gsgnq7rj2j0","decimals":null,"volume":"44","symbol":"Ebooks, AudioBooks, Pictures"},{"hash":"zil1de9ey6dztk9w6qmlzug52wcks0mx43p0enmsgf","decimals":null,"volume":"2","symbol":"Hype-collectible "},{"hash":"zil19qe48mlvmng7hqf9l2zwd2e4838gzwya76njr5","decimals":null,"volume":"2","symbol":"Verrockstar Material"},{"hash":"zil1msqhtgm0s9ymqwg0z80gv8kx9vglfgdn779kdg","decimals":null,"volume":"5","symbol":"Cars"},{"hash":"zil146j7c5ttmxc7gevfkqqmyu53zaktzzx0n82qwn","decimals":null,"volume":"9","symbol":"Trance &  Electronic"},{"hash":"zil1zk9yy9kt824qlx7666wpk8rtsfae7qvzw5ztfx","decimals":null,"volume":"30","symbol":"HASH"},{"hash":"zil1npjze05vfc228k92zmg479qv2p5xumre2t933w","decimals":null,"volume":"13","symbol":"A collection of some coll NFT  "},{"hash":"zil10k24syejup7t7svnq8z6dsddxe38ys5n5ptehx","decimals":null,"volume":"1","symbol":"Create and sell unique item with limited supply"},{"hash":"zil10w4nhelcmyvfc0aaw5resqx2dc9rgjwxlpjtrc","decimals":null,"volume":"2","symbol":"Fun-time art and collectibles on the blockchain"},{"hash":"zil17tsmlqgnzlfxsq4evm6n26txm2xlp5hele0kew","decimals":6,"volume":"55120071615064","symbol":"SHRK"},{"hash":"zil197xj5zjt0nh8egpdvgh8q7c9nxer6cfjrjk79h","decimals":6,"volume":"88888","symbol":"PIG"},{"hash":"zil1mjuh3dwqd3w8kkjt0rchgtpp0gy5qr0vatqjaz","decimals":18,"volume":"20750000000000000000000","symbol":"RUG"},{"hash":"zil10z935x2sj8rc35vvfhfk23m4lqlcsl43jm4kh5","decimals":18,"volume":"100000000000000000000","symbol":"TYGC"},{"hash":"zil1r7jth00fwv47vn9503zgynjmpepf6amqksk8pn","decimals":null,"volume":"42","symbol":"Exclusive "},{"hash":"zil10k6te074qfmlmujh6gfcrv8v7u4vulpg7hfehn","decimals":18,"volume":"100000000000000000000","symbol":"JAYC"},{"hash":"zil1050h6ckf9429mjdjla0alhx6apf3jd3yhvgklj","decimals":18,"volume":"40500000000000000000000","symbol":"SAC"},{"hash":"zil1a5wkhunysdp9x0nww5qe6m2m8x2m3ygdpuu257","decimals":2,"volume":"2466400","symbol":"RedC"},{"hash":"zil1jcefap5k2e90dagy37hzgjda38cr5kuf85hfpt","decimals":0,"volume":"1527","symbol":"1337"},{"hash":"zil1llty8xjeakaxh66ftsz650ks2ld4np7sdq3f65","decimals":18,"volume":"1","symbol":"DRIFT"}],"networkVolumeRune":null,"networkVolumeUSD":null},{"timestamp":1601856000000,"creationCount":2250,"tokenCreationCount":122,"txCount":1165149,"growthCount":139275,"reward":131403260.8335571,"staked":"2956943646","buffer":"3074512819","tokens":[{"hash":"zil1llty8xjeakaxh66ftsz650ks2ld4np7sdq3f65","decimals":18,"volume":"2001100","symbol":"DRIFT"},{"hash":"zil180v66mlw007ltdv8tq5t240y7upwgf7djklmwh","decimals":6,"volume":"1467686973850","symbol":"XSGD"},{"hash":"zil1jgeg36neay6xlcv9k07zp8v55dvacq2h3yed7a","decimals":2,"volume":"12869","symbol":"DRIFT"},{"hash":"zil1x6z064fkssmef222gkhz3u5fhx57kyssn7vlu0","decimals":18,"volume":"1586265546651131991227572","symbol":"BOLT"},{"hash":"zil17tsmlqgnzlfxsq4evm6n26txm2xlp5hele0kew","decimals":6,"volume":"357332963","symbol":"SHRK"},{"hash":"zil1050h6ckf9429mjdjla0alhx6apf3jd3yhvgklj","decimals":18,"volume":"11094680661802026071758","symbol":"SAC"},{"hash":"zil1r7jth00fwv47vn9503zgynjmpepf6amqksk8pn","decimals":null,"volume":"11","symbol":"Exclusive "},{"hash":"zil17wwksg2jzder2l92xehfyk92cwp3qsexw4frfz","decimals":null,"volume":"154","symbol":"Music Collectibles"},{"hash":"zil1gygumfzwpgna6q5mssg9e3nmvuqdql7wjzjtuk","decimals":3,"volume":"55858939888","symbol":"ZILLB"},{"hash":"zil1l0g8u6f9g0fsvjuu74ctyla2hltefrdyt7k5f4","decimals":18,"volume":"923804841315287754772823","symbol":"ZLP"},{"hash":"zil1hau7z6rjltvjc95pphwj57umdpvv0d6kh2t8zk","decimals":8,"volume":"732341019944","symbol":"CARB"},{"hash":"zil1a5wkhunysdp9x0nww5qe6m2m8x2m3ygdpuu257","decimals":2,"volume":"1249288","symbol":"RedC"},{"hash":"zil1arrjugcg28rw8g9zxpa6qffc6wekpwk2alu7kj","decimals":3,"volume":"336481109","symbol":"ZYF"},{"hash":"zil1a5djlwvm28zf9r75x6es0gjaputfd67n7h0092","decimals":5,"volume":"448014935","symbol":"Pi"},{"hash":"zil1hzy9ccdhugflcnhfkl9ysm7cxazeff3s6s9ngx","decimals":6,"volume":"7764283366958","symbol":"ZGLD"},{"hash":"zil13zmkv6ced5rnrkvrmm8dn6jx49nkf7evevgal5","decimals":null,"volume":"152","symbol":"Imagine the unimaginable and possess "},{"hash":"zil1q5zy7x4ap6jkkfp3g6yymegr48ttaezplamt3j","decimals":6,"volume":"10408747346","symbol":"HBN"},{"hash":"zil1exxy0hm74ftq3xnp4wf3y2yvyh3z58vxpnvhq2","decimals":2,"volume":"1854","symbol":"ZCT"},{"hash":"zil14pzuzq6v6pmmmrfjhczywguu0e97djepxt8g3e","decimals":15,"volume":"35828553395497947695","symbol":"gZIL"},{"hash":"zil1ztmv5jhfpnxu95ts9ylup7hj73n5ka744jm4ea","decimals":5,"volume":"44654136251","symbol":"SERGS"},{"hash":"zil1jg3vg4mnkzsnatf75nyzsjhdtlq25umz4evxd4","decimals":6,"volume":"427222814","symbol":"AMP"},{"hash":"zil1r9dcsrya4ynuxnzaznu00e6hh3kpt7vhvzgva0","decimals":5,"volume":"36733631","symbol":"ZLF"},{"hash":"zil1awc3fxmmuqf92gzlxwu76s85jsrcsm2cv39n5p","decimals":6,"volume":"55875285636","symbol":"ZLM"},{"hash":"zil1kapwt00c2jgjw7sruphsyhfs7tzxqzal2wm69w","decimals":8,"volume":"7231302688224","symbol":"DGB"},{"hash":"zil1n2dthjaszmf0c4rr2hflna06wfkdvqrt3akadn","decimals":3,"volume":"382713","symbol":"ZRC"}],"networkVolumeRune":null,"networkVolumeUSD":null},{"timestamp":1604448000000,"creationCount":1923,"tokenCreationCount":24,"txCount":1027409,"growthCount":91882,"reward":133650000,"staked":"3765190834","buffer":"1179335294","tokens":[{"hash":"zil14pzuzq6v6pmmmrfjhczywguu0e97djepxt8g3e","decimals":15,"volume":"72247875726486390194","symbol":"gZIL"},{"hash":"zil1hau7z6rjltvjc95pphwj57umdpvv0d6kh2t8zk","decimals":8,"volume":"316435657487","symbol":"CARB"},{"hash":"zil1l0g8u6f9g0fsvjuu74ctyla2hltefrdyt7k5f4","decimals":18,"volume":"117980751693232086266975","symbol":"ZLP"},{"hash":"zil1ucvrn22x8366vzpw5t7su6eyml2auczu6wnqqg","decimals":8,"volume":"92569608040351","symbol":"ZYRO"},{"hash":"zil1262rjxyvurw9q9ssc24gct99hx7akhljun694f","decimals":6,"volume":"438692488","symbol":"SWAP"},{"hash":"zil180v66mlw007ltdv8tq5t240y7upwgf7djklmwh","decimals":6,"volume":"16192296618","symbol":"XSGD"},{"hash":"zil1x6z064fkssmef222gkhz3u5fhx57kyssn7vlu0","decimals":18,"volume":"27099707536818345442904","symbol":"BOLT"},{"hash":"zil1gygumfzwpgna6q5mssg9e3nmvuqdql7wjzjtuk","decimals":3,"volume":"221500884","symbol":"ZILLB"},{"hash":"zil1ztmv5jhfpnxu95ts9ylup7hj73n5ka744jm4ea","decimals":5,"volume":"8578900801","symbol":"SERGS"},{"hash":"zil1mweyuj5gg0zcwt5ra8u76jskj7c3tkqj5kprm3","decimals":6,"volume":"2583705929","symbol":"LOOM"},{"hash":"zil1r9dcsrya4ynuxnzaznu00e6hh3kpt7vhvzgva0","decimals":5,"volume":"14779538","symbol":"ZLF"},{"hash":"zil17tsmlqgnzlfxsq4evm6n26txm2xlp5hele0kew","decimals":6,"volume":"7142719","symbol":"SHRK"},{"hash":"zil1a5wkhunysdp9x0nww5qe6m2m8x2m3ygdpuu257","decimals":2,"volume":"100000","symbol":"RedC"},{"hash":"zil12zvwp9j78jygy9x7mezgw6ur0mwltj06qkr2ft","decimals":8,"volume":"67039396779911","symbol":"ZLPT"}],"networkVolumeRune":null,"networkVolumeUSD":null},{"timestamp":1607040000000,"creationCount":2661,"tokenCreationCount":16,"txCount":1017794,"growthCount":96931,"reward":114675000,"staked":"4379771531","buffer":"1009406535","tokens":[{"hash":"zil14pzuzq6v6pmmmrfjhczywguu0e97djepxt8g3e","decimals":15,"volume":"85594806073958124390","symbol":"gZIL"},{"hash":"zil180v66mlw007ltdv8tq5t240y7upwgf7djklmwh","decimals":6,"volume":"29196362701","symbol":"XSGD"},{"hash":"zil1x6z064fkssmef222gkhz3u5fhx57kyssn7vlu0","decimals":18,"volume":"32984623274748471357587","symbol":"BOLT"},{"hash":"zil1r9dcsrya4ynuxnzaznu00e6hh3kpt7vhvzgva0","decimals":5,"volume":"48286402","symbol":"ZLF"},{"hash":"zil1ucvrn22x8366vzpw5t7su6eyml2auczu6wnqqg","decimals":8,"volume":"469067783405298","symbol":"ZYRO"},{"hash":"zil1a5wkhunysdp9x0nww5qe6m2m8x2m3ygdpuu257","decimals":2,"volume":"160806","symbol":"RedC"},{"hash":"zil1ztmv5jhfpnxu95ts9ylup7hj73n5ka744jm4ea","decimals":5,"volume":"47005044","symbol":"SERGS"},{"hash":"zil1arrjugcg28rw8g9zxpa6qffc6wekpwk2alu7kj","decimals":3,"volume":"1056784575","symbol":"ZYF"},{"hash":"zil1yra4pfe46qh7j9cvrhgtj4v0rjk380kwxp93qa","decimals":5,"volume":"400000000","symbol":"ZILD"},{"hash":"zil1hau7z6rjltvjc95pphwj57umdpvv0d6kh2t8zk","decimals":8,"volume":"203562222104","symbol":"CARB"},{"hash":"zil18f5rlhqz9vndw4w8p60d0n7vg3n9sqvta7n6t2","decimals":4,"volume":"8499988000","symbol":"PORT"},{"hash":"zil1p2cp77kz06wlxeyha4psawencm5gx8ttcwsxdn","decimals":5,"volume":"1958","symbol":"KKZ"},{"hash":"zil1l0g8u6f9g0fsvjuu74ctyla2hltefrdyt7k5f4","decimals":18,"volume":"1435071061696121501839","symbol":"ZLP"},{"hash":"zil1hzy9ccdhugflcnhfkl9ysm7cxazeff3s6s9ngx","decimals":6,"volume":"1501769147247","symbol":"ZGLD"}],"networkVolumeRune":null,"networkVolumeUSD":null},{"timestamp":1609632000000,"creationCount":2314,"tokenCreationCount":25,"txCount":952826,"growthCount":85957,"reward":124575000,"staked":"4723034029","buffer":"751583606","tokens":[{"hash":"zil14pzuzq6v6pmmmrfjhczywguu0e97djepxt8g3e","decimals":15,"volume":"87890067057870202011","symbol":"gZIL"},{"hash":"zil1ucvrn22x8366vzpw5t7su6eyml2auczu6wnqqg","decimals":8,"volume":"406436629125429","symbol":"ZYRO"},{"hash":"zil1r9dcsrya4ynuxnzaznu00e6hh3kpt7vhvzgva0","decimals":5,"volume":"17160636","symbol":"ZLF"},{"hash":"zil180v66mlw007ltdv8tq5t240y7upwgf7djklmwh","decimals":6,"volume":"51840604346","symbol":"XSGD"},{"hash":"zil1x6z064fkssmef222gkhz3u5fhx57kyssn7vlu0","decimals":18,"volume":"212676213492597928804269","symbol":"BOLT"},{"hash":"zil1l0g8u6f9g0fsvjuu74ctyla2hltefrdyt7k5f4","decimals":18,"volume":"8093980120953265619114","symbol":"ZLP"},{"hash":"zil17tsmlqgnzlfxsq4evm6n26txm2xlp5hele0kew","decimals":6,"volume":"32811259","symbol":"SHRK"},{"hash":"zil1arrjugcg28rw8g9zxpa6qffc6wekpwk2alu7kj","decimals":3,"volume":"10986359","symbol":"ZYF"}],"networkVolumeRune":null,"networkVolumeUSD":null},{"timestamp":1612224000000,"creationCount":3608,"tokenCreationCount":161,"txCount":2256708,"growthCount":106424,"reward":126225000,"staked":"4532046557","buffer":"621261118","tokens":[{"hash":"zil1ucvrn22x8366vzpw5t7su6eyml2auczu6wnqqg","decimals":8,"volume":"550758365727073","symbol":"ZYRO"},{"hash":"zil14pzuzq6v6pmmmrfjhczywguu0e97djepxt8g3e","decimals":15,"volume":"233678887421342611006","symbol":"gZIL"},{"hash":"zil1nfdv07wrzjwetck4c5qscdhm4x9s3zdzhkkg88","decimals":8,"volume":"605504729304072","symbol":"ZLPT"},{"hash":"zil1a5wkhunysdp9x0nww5qe6m2m8x2m3ygdpuu257","decimals":2,"volume":"805","symbol":"RedC"},{"hash":"zil17j8zpddnhuhfyyqg5nc2aywk0sffdqhs3zjs7u","decimals":8,"volume":"16939873214759056","symbol":"ZLPT"},{"hash":"zil1p5suryq6q647usxczale29cu3336hhp376c627","decimals":12,"volume":"51453865529548349","symbol":"ZWAP"},{"hash":"zil180v66mlw007ltdv8tq5t240y7upwgf7djklmwh","decimals":6,"volume":"3062157348016","symbol":"XSGD"},{"hash":"zil18f5rlhqz9vndw4w8p60d0n7vg3n9sqvta7n6t2","decimals":4,"volume":"18333466","symbol":"PORT"},{"hash":"zil1x6z064fkssmef222gkhz3u5fhx57kyssn7vlu0","decimals":18,"volume":"14855669857080653480904","symbol":"BOLT"},{"hash":"zil1l0g8u6f9g0fsvjuu74ctyla2hltefrdyt7k5f4","decimals":18,"volume":"18088104549668353558059","symbol":"ZLP"},{"hash":"zil17tsmlqgnzlfxsq4evm6n26txm2xlp5hele0kew","decimals":6,"volume":"2657527075","symbol":"SHRK"},{"hash":"zil1n2dthjaszmf0c4rr2hflna06wfkdvqrt3akadn","decimals":3,"volume":"12005424","symbol":"ZRC"},{"hash":"zil1y7383h0w3483eppc4x8e9z55u36ttehpl04lj7","decimals":null,"volume":"3","symbol":"@AlienCardano"},{"hash":"zil1axggec2ghge4h9y0dh2s84473n4007sma49xh7","decimals":null,"volume":"86","symbol":"premium exclusive concept art"},{"hash":"zil1d6u5r76ea3mr4hwggvdsjva88zz45jlllt9gn0","decimals":null,"volume":"76","symbol":"A finely curated selection of artwork. Available in NFT format."}],"networkVolumeRune":null,"networkVolumeUSD":null},{"timestamp":1614816000000,"creationCount":7198,"tokenCreationCount":528,"txCount":1511674,"growthCount":134179,"reward":130350000,"staked":"4662512108","buffer":"682039571","tokens":[{"hash":"zil180v66mlw007ltdv8tq5t240y7upwgf7djklmwh","decimals":6,"volume":"19787525163615","symbol":"XSGD"},{"hash":"zil14pzuzq6v6pmmmrfjhczywguu0e97djepxt8g3e","decimals":15,"volume":"229658272178667382380","symbol":"gZIL"},{"hash":"zil1ucvrn22x8366vzpw5t7su6eyml2auczu6wnqqg","decimals":8,"volume":"1212398359583608","symbol":"ZYRO"},{"hash":"zil1p5suryq6q647usxczale29cu3336hhp376c627","decimals":12,"volume":"83839093991311145","symbol":"ZWAP"},{"hash":"zil18f5rlhqz9vndw4w8p60d0n7vg3n9sqvta7n6t2","decimals":4,"volume":"1340506221","symbol":"PORT"},{"hash":"zil1l0g8u6f9g0fsvjuu74ctyla2hltefrdyt7k5f4","decimals":18,"volume":"321504509502830921550773","symbol":"ZLP"},{"hash":"zil1r9dcsrya4ynuxnzaznu00e6hh3kpt7vhvzgva0","decimals":5,"volume":"141717351","symbol":"ZLF"},{"hash":"zil1x6z064fkssmef222gkhz3u5fhx57kyssn7vlu0","decimals":18,"volume":"243427770336119275351997","symbol":"BOLT"},{"hash":"zil1rk9vdfu2xsp7y4h24qg78n6ss23mxxge5slsv2","decimals":6,"volume":"9993998454","symbol":"AXT"},{"hash":"zil1apmtzy4x9729fp8du8euehttptr08yuzamfy9f","decimals":null,"volume":"2650","symbol":"DZT"},{"hash":"zil17zvlqn2xamqpumlm2pgul9nezzd3ydmrufxnct","decimals":2,"volume":"185159","symbol":"BARTER"},{"hash":"zil14jmjrkvfcz2uvj3y69kl6gas34ecuf2j5ggmye","decimals":9,"volume":"9760537203898","symbol":"REDC"},{"hash":"zil1hzy9ccdhugflcnhfkl9ysm7cxazeff3s6s9ngx","decimals":6,"volume":"212850713102","symbol":"ZGLD"},{"hash":"zil1hau7z6rjltvjc95pphwj57umdpvv0d6kh2t8zk","decimals":8,"volume":"3457407663656","symbol":"CARB"},{"hash":"zil1arrjugcg28rw8g9zxpa6qffc6wekpwk2alu7kj","decimals":3,"volume":"49419891","symbol":"ZYF"},{"hash":"zil17tsmlqgnzlfxsq4evm6n26txm2xlp5hele0kew","decimals":6,"volume":"7083358552","symbol":"SHRK"},{"hash":"zil1lwynjvthuzatnjcgvekuwf5aa8aqwvr5ygwvsq","decimals":null,"volume":"3","symbol":"Art in photos"},{"hash":"zil1s8xzysqcxva2x6aducncv9um3zxr36way3fx9g","decimals":6,"volume":"5185811563","symbol":"ZCH"},{"hash":"zil1tah6wdxlfgnq89t2uaea5ha6gy845jpn8w2y96","decimals":null,"volume":"11","symbol":"Abstract Colours"},{"hash":"zil12fy6ru96jud7yvtgppvp7mpsakzz8ysmvnagqt","decimals":6,"volume":"28541588","symbol":"ZLEND"},{"hash":"zil1w5hwupgc9rxyuyd742g2c9annwahugrx80fw9h","decimals":4,"volume":"20963","symbol":"GARY"},{"hash":"zil1ztmv5jhfpnxu95ts9ylup7hj73n5ka744jm4ea","decimals":5,"volume":"664625191","symbol":"SERGS"},{"hash":"zil1kapwt00c2jgjw7sruphsyhfs7tzxqzal2wm69w","decimals":8,"volume":"371518729329","symbol":"DGB"},{"hash":"zil105lwcl5ckrrl2ljhq8v2360vhy30wy85wgvmym","decimals":0,"volume":"20337671","symbol":"GOD"},{"hash":"zil1lr4ckncg6q6grqlcsmx7fx6y9v85lc3vrctn4c","decimals":null,"volume":"1","symbol":"for Unique NFT's "},{"hash":"zil1c6akv8k6dqaac7ft8ezk5gr2jtxrewfw8hc27d","decimals":2,"volume":"5864","symbol":"DUCK"},{"hash":"zil1aksx0waznmssr9dhu2eqsru5pzxc4p9s7mm7cc","decimals":18,"volume":"60277679832337267801733","symbol":"IGA"},{"hash":"zil1zkjqvk9uq023mc6fe746narshchv3ml24mamzc","decimals":0,"volume":"19891","symbol":"COOL"},{"hash":"zil1lq3ghn3yaqk0w7fqtszv53hejunpyfyh3rx9gc","decimals":3,"volume":"17561","symbol":"Elons"},{"hash":"zil10w6ukup76ljmvgn4c25e5kpkjehe6a7vqa5r3y","decimals":4,"volume":"116729980674","symbol":"ZPN"},{"hash":"zil183a4hyqx526nmp5e6w2eza8tkf72l07h7m9d4v","decimals":3,"volume":"1212766","symbol":"Bezos"},{"hash":"zil1g85eeqe8pl8g4ngqncl83m4d8yuyugvn6g9055","decimals":8,"volume":"1307332113960631","symbol":"COVID-19"},{"hash":"zil12d6pnwj599p2yhdzamcuguvawp4u8wg54a394x","decimals":3,"volume":"89306630816","symbol":"SafePay"},{"hash":"zil1lwpx2a68jtd3vjkjm6n6nuagkg0ge9dl9hyre0","decimals":4,"volume":"1812905","symbol":"NFT"},{"hash":"zil1dt7m7eda36fa28d75a7jquaed88v4f8k73s8eq","decimals":8,"volume":"20722771750","symbol":"Mobster"},{"hash":"zil1xlxu8qjj2v7gj7pqprezg2dadaa74uxwtqg6q6","decimals":3,"volume":"82922220740","symbol":"ZRT"},{"hash":"zil1ckqvrnhq0njjmzqy2jkp3np35yvpvhajs33fa4","decimals":3,"volume":"134493401","symbol":"zDAO"},{"hash":"zil1eka4am8tmau6t8gg0sxqpvrhhtke4rdfsww0cn","decimals":null,"volume":"39","symbol":"UFFS_SCO_PASS__PROMO_NFT"},{"hash":"zil1yq7vda8ryfhl3s8askm3t7qpmqrh3nz3vlj2p9","decimals":null,"volume":"326","symbol":"passionate hobby art made by intelligent style programms and only choosen by human(me)"}],"networkVolumeRune":null,"networkVolumeUSD":null},{"timestamp":1617408000000,"creationCount":4422,"tokenCreationCount":418,"txCount":2524430,"growthCount":205461,"reward":134200000,"staked":"4770574590","buffer":"574158577","tokens":[{"hash":"zil14pzuzq6v6pmmmrfjhczywguu0e97djepxt8g3e","decimals":15,"volume":"174199113496959864494","symbol":"gZIL"},{"hash":"zil18f5rlhqz9vndw4w8p60d0n7vg3n9sqvta7n6t2","decimals":4,"volume":"75059270466","symbol":"PORT"},{"hash":"zil180v66mlw007ltdv8tq5t240y7upwgf7djklmwh","decimals":6,"volume":"23893420307800","symbol":"XSGD"},{"hash":"zil1ucvrn22x8366vzpw5t7su6eyml2auczu6wnqqg","decimals":8,"volume":"276054842241576","symbol":"ZYRO"},{"hash":"zil1p5suryq6q647usxczale29cu3336hhp376c627","decimals":12,"volume":"41290624751915045","symbol":"ZWAP"},{"hash":"zil12zy4485925ces3esn9zcc8pn9ldljk4usq7dz5","decimals":6,"volume":"16669309567","symbol":"WBET"},{"hash":"zil1eka4am8tmau6t8gg0sxqpvrhhtke4rdfsww0cn","decimals":null,"volume":"21","symbol":"UFFS_SCO_PASS__PROMO_NFT"},{"hash":"zil1w5hwupgc9rxyuyd742g2c9annwahugrx80fw9h","decimals":4,"volume":"1000","symbol":"GARY"},{"hash":"zil1l0g8u6f9g0fsvjuu74ctyla2hltefrdyt7k5f4","decimals":18,"volume":"39601708286712126272498","symbol":"ZLP"},{"hash":"zil17zvlqn2xamqpumlm2pgul9nezzd3ydmrufxnct","decimals":2,"volume":"102478","symbol":"BARTER"},{"hash":"zil1fd5gk50l0xvf4wd9mylpgw26t4rhlm75ahuu35","decimals":4,"volume":"12308678708238","symbol":"Bees"},{"hash":"zil1s8xzysqcxva2x6aducncv9um3zxr36way3fx9g","decimals":6,"volume":"80083349814","symbol":"ZCH"},{"hash":"zil10w6ukup76ljmvgn4c25e5kpkjehe6a7vqa5r3y","decimals":4,"volume":"184874235","symbol":"ZPN"},{"hash":"zil1gvr0jgwfsfmxsyx0xsnhtlte4gks6r3yk8x5fn","decimals":12,"volume":"4420000000006702","symbol":"wZIL"},{"hash":"zil168qdlq4xsua6ac9hugzntqyasf8gs7aund882v","decimals":2,"volume":"1536505","symbol":"SRV"},{"hash":"zil12drvflckms6874ffuujcdxj75raavl4yfn4ssc","decimals":12,"volume":"22202839347419033","symbol":"RECAP"},{"hash":"zil14jmjrkvfcz2uvj3y69kl6gas34ecuf2j5ggmye","decimals":9,"volume":"4719911904552","symbol":"REDC"},{"hash":"zil1s4n5hlxpy5aasmmanac8jdhp39xxcdekvqvkx9","decimals":6,"volume":"738191451709","symbol":"TKO"},{"hash":"zil1c6akv8k6dqaac7ft8ezk5gr2jtxrewfw8hc27d","decimals":2,"volume":"442","symbol":"DUCK"},{"hash":"zil1vx0t8cz9s033c0pwwzyw5eq8dzufe2kac94kae","decimals":3,"volume":"105149129","symbol":"GRT"},{"hash":"zil19m8lktnccvsg6v5d3rvq2weuj67uprfczd340l","decimals":5,"volume":"10512395249","symbol":"ZGG"},{"hash":"zil1pdxm02u4v6wmjtwswqm305uyth2lkwurawkvre","decimals":5,"volume":"661500719","symbol":"TT"},{"hash":"zil1hau7z6rjltvjc95pphwj57umdpvv0d6kh2t8zk","decimals":8,"volume":"14149392626209","symbol":"CARB"},{"hash":"zil1apmtzy4x9729fp8du8euehttptr08yuzamfy9f","decimals":null,"volume":"2621","symbol":"DZT"},{"hash":"zil1yq7vda8ryfhl3s8askm3t7qpmqrh3nz3vlj2p9","decimals":null,"volume":"224","symbol":"passionate hobby art made by intelligent style programms and only choosen by human(me)"},{"hash":"zil1hpwshtxspjakjh5sn7vn4e7pp4gaqkefup24h2","decimals":4,"volume":"4100250","symbol":"XPORT"},{"hash":"zil1a2n5f8du90uh5j7vzjq96rc52ga9svyf8jjr93","decimals":null,"volume":"54","symbol":"All are welcome"},{"hash":"zil1r9dcsrya4ynuxnzaznu00e6hh3kpt7vhvzgva0","decimals":5,"volume":"38557449","symbol":"ZLF"},{"hash":"zil1n6fdw4te0m6ukrfc5sg09x8h8vxl25aa8wpv9h","decimals":null,"volume":"3","symbol":"Welcome to the realm"},{"hash":"zil105lwcl5ckrrl2ljhq8v2360vhy30wy85wgvmym","decimals":0,"volume":"14459743","symbol":"GOD"},{"hash":"zil1vl4cq3vdw94cf859kuaz2qm5gp0lpqjp3dqqpa","decimals":null,"volume":"70","symbol":"Meteorite Gigapixel Mosaics"},{"hash":"zil1vrapc654veptmvsan09k7rypddluancv70uszr","decimals":null,"volume":"2","symbol":"Precious NFTs"},{"hash":"zil1h80ngwhgy68dmktnsqxaw9p5470m6gwa6anupg","decimals":null,"volume":"10","symbol":"Nazzy's Digital Art Store"},{"hash":"zil1kwfu3x9n6fsuxc4ynp72uk5rxge25enw7zsf9z","decimals":4,"volume":"10672010000","symbol":"SCO"}],"networkVolumeRune":null,"networkVolumeUSD":null},{"timestamp":1620000000000,"creationCount":3196,"tokenCreationCount":179,"txCount":1584157,"growthCount":170944,"reward":116032000,"staked":"4772897564","buffer":"293892849","tokens":[{"hash":"zil14pzuzq6v6pmmmrfjhczywguu0e97djepxt8g3e","decimals":15,"volume":"120472642835766268066","symbol":"gZIL"},{"hash":"zil1s8xzysqcxva2x6aducncv9um3zxr36way3fx9g","decimals":6,"volume":"130471538951","symbol":"ZCH"},{"hash":"zil18f5rlhqz9vndw4w8p60d0n7vg3n9sqvta7n6t2","decimals":4,"volume":"3738306357","symbol":"PORT"},{"hash":"zil180v66mlw007ltdv8tq5t240y7upwgf7djklmwh","decimals":6,"volume":"54354886931404","symbol":"XSGD"},{"hash":"zil1l0g8u6f9g0fsvjuu74ctyla2hltefrdyt7k5f4","decimals":18,"volume":"67128645308752811342144","symbol":"ZLP"},{"hash":"zil1kwfu3x9n6fsuxc4ynp72uk5rxge25enw7zsf9z","decimals":4,"volume":"35110000497","symbol":"SCO"},{"hash":"zil1p5suryq6q647usxczale29cu3336hhp376c627","decimals":12,"volume":"43169365435201901","symbol":"ZWAP"},{"hash":"zil1ucvrn22x8366vzpw5t7su6eyml2auczu6wnqqg","decimals":8,"volume":"444487767035114","symbol":"ZYRO"},{"hash":"zil1r9dcsrya4ynuxnzaznu00e6hh3kpt7vhvzgva0","decimals":5,"volume":"194714752","symbol":"ZLF"},{"hash":"zil1hau7z6rjltvjc95pphwj57umdpvv0d6kh2t8zk","decimals":8,"volume":"7844245279256","symbol":"CARB"},{"hash":"zil14jmjrkvfcz2uvj3y69kl6gas34ecuf2j5ggmye","decimals":9,"volume":"19452532634364","symbol":"REDC"},{"hash":"zil168qdlq4xsua6ac9hugzntqyasf8gs7aund882v","decimals":2,"volume":"256051","symbol":"SRV"},{"hash":"zil1hpwshtxspjakjh5sn7vn4e7pp4gaqkefup24h2","decimals":4,"volume":"116891395","symbol":"XPORT"},{"hash":"zil1z99wjqd57rge9q08xmca6aktvg8sr3f7mpj5cv","decimals":3,"volume":"27871000","symbol":"LUCKY"},{"hash":"zil1zra5mzhu0lswuhq7k85vyks3asahz9pjetwatd","decimals":null,"volume":"6","symbol":"gET IT"},{"hash":"zil1knvrhm9e2rqfdvqp50gu02a3pat34e6lst9d36","decimals":null,"volume":"35703","symbol":"DZT"},{"hash":"zil1sgdw5xgcpvyx3u3rqy287rpgyppg85t8dwyydr","decimals":null,"volume":"1654","symbol":"UFFSNFT"},{"hash":"zil105lwcl5ckrrl2ljhq8v2360vhy30wy85wgvmym","decimals":0,"volume":"6259487","symbol":"GOD"},{"hash":"zil1lq3ghn3yaqk0w7fqtszv53hejunpyfyh3rx9gc","decimals":3,"volume":"5910","symbol":"Elons"},{"hash":"zil12drvflckms6874ffuujcdxj75raavl4yfn4ssc","decimals":12,"volume":"23583669971386346","symbol":"RECAP"},{"hash":"zil17tsmlqgnzlfxsq4evm6n26txm2xlp5hele0kew","decimals":6,"volume":"2458439608","symbol":"SHRK"},{"hash":"zil1rk9vdfu2xsp7y4h24qg78n6ss23mxxge5slsv2","decimals":6,"volume":"45000000","symbol":"AXT"},{"hash":"zil1h63h5rlg7avatnlzhfnfzwn8vfspwkapzdy2aw","decimals":6,"volume":"97080818325","symbol":"XCAD"},{"hash":"zil1jzgqy7kv3uth5kwm9kcagrh0ezutw2qmjxp4zf","decimals":0,"volume":"770628","symbol":"ZGEMS"}],"networkVolumeRune":null,"networkVolumeUSD":null},{"timestamp":1622592000000,"creationCount":3853,"tokenCreationCount":202,"txCount":1399282,"growthCount":151246,"reward":123216000,"staked":"5000366700","buffer":"506343523","tokens":[{"hash":"zil18f5rlhqz9vndw4w8p60d0n7vg3n9sqvta7n6t2","decimals":4,"volume":"5464359187","symbol":"PORT"},{"hash":"zil1rffxmkjvce5ytfw4yt7chnag7fv6a6vphfxush","decimals":null,"volume":"2","symbol":"Right in my heart"},{"hash":"zil180v66mlw007ltdv8tq5t240y7upwgf7djklmwh","decimals":6,"volume":"14604943512532","symbol":"XSGD"},{"hash":"zil1kwfu3x9n6fsuxc4ynp72uk5rxge25enw7zsf9z","decimals":4,"volume":"6524638626","symbol":"SCO"},{"hash":"zil14pzuzq6v6pmmmrfjhczywguu0e97djepxt8g3e","decimals":15,"volume":"59959863532677962776","symbol":"gZIL"},{"hash":"zil1p5suryq6q647usxczale29cu3336hhp376c627","decimals":12,"volume":"35525878279212389","symbol":"ZWAP"},{"hash":"zil1c6akv8k6dqaac7ft8ezk5gr2jtxrewfw8hc27d","decimals":2,"volume":"99","symbol":"DUCK"},{"hash":"zil1s8xzysqcxva2x6aducncv9um3zxr36way3fx9g","decimals":6,"volume":"125565869159","symbol":"ZCH"},{"hash":"zil1ucvrn22x8366vzpw5t7su6eyml2auczu6wnqqg","decimals":8,"volume":"169734263868178","symbol":"ZYRO"},{"hash":"zil18lnyaze7ncgsmve3kvh2ymsersrlznuq0j3uxs","decimals":null,"volume":"6257407072","symbol":"ZILSTARS-NFT"},{"hash":"zil1h63h5rlg7avatnlzhfnfzwn8vfspwkapzdy2aw","decimals":6,"volume":"7163253727","symbol":"XCAD"},{"hash":"zil1hau7z6rjltvjc95pphwj57umdpvv0d6kh2t8zk","decimals":8,"volume":"4691695272792","symbol":"CARB"},{"hash":"zil1hpwshtxspjakjh5sn7vn4e7pp4gaqkefup24h2","decimals":4,"volume":"97232540","symbol":"XPORT"},{"hash":"zil1lq3ghn3yaqk0w7fqtszv53hejunpyfyh3rx9gc","decimals":3,"volume":"5718","symbol":"Elons"},{"hash":"zil12drvflckms6874ffuujcdxj75raavl4yfn4ssc","decimals":12,"volume":"1593089583553000","symbol":"RECAP"},{"hash":"zil14jmjrkvfcz2uvj3y69kl6gas34ecuf2j5ggmye","decimals":9,"volume":"182627809575","symbol":"REDC"},{"hash":"zil1dccsly0lwkkxhxxazldcnph05v2dz8maz46g05","decimals":4,"volume":"80000","symbol":"RWD"},{"hash":"zil168qdlq4xsua6ac9hugzntqyasf8gs7aund882v","decimals":2,"volume":"967246","symbol":"SRV"},{"hash":"zil17sraylya0025nuhjwx6e039k3v3ay7zk7lun3u","decimals":12,"volume":"390000000000000","symbol":"WZIL"},{"hash":"zil1ykcdhtgyercmv7ndfxt00wm9xzpq4k7hjmfm4e","decimals":12,"volume":"604574243346362495","symbol":"MAMBO"},{"hash":"zil1qzwxvp3wz3q5ewzg3afesut9pqfax0sjdyna42","decimals":2,"volume":"524559","symbol":"MESSI"},{"hash":"zil1504065pp76uuxm7s9m2c4gwszhez8pu3mp6r8c","decimals":8,"volume":"157639391140096","symbol":"STREAM"},{"hash":"zil1pv0vztktc3aeq3kfvpyzujm2jvejlnd094hlug","decimals":8,"volume":"32613300000000","symbol":"Free"},{"hash":"zil1xlqfr35wyejf82502p9hse84a4uzjkrppefk08","decimals":null,"volume":"30","symbol":"Setting video to music."},{"hash":"zil1p5a30n55ek790f99zh8l27s0l8f0axrjes07sq","decimals":5,"volume":"81357447259","symbol":"WOJAK"},{"hash":"zil1l0g8u6f9g0fsvjuu74ctyla2hltefrdyt7k5f4","decimals":18,"volume":"32808553535199079913727","symbol":"ZLP"},{"hash":"zil1vsxlvznhtxtlpuhs948gpzylgsmyufqmw2j32f","decimals":4,"volume":"13930","symbol":"APE"},{"hash":"zil1pqcev4ykxla0jhy3anx32lnqgv8xncd8q57ql2","decimals":4,"volume":"11200287887","symbol":"SPW"},{"hash":"zil1r32n9p5u5k99u5nl5tjvndyy0mjpcdvswzmu7w","decimals":4,"volume":"6000000","symbol":"Tesla"},{"hash":"zil1knvrhm9e2rqfdvqp50gu02a3pat34e6lst9d36","decimals":null,"volume":"3373","symbol":"DZT"}],"networkVolumeRune":null,"networkVolumeUSD":null},{"timestamp":1625184000000,"creationCount":2279,"tokenCreationCount":112,"txCount":1159481,"growthCount":143840,"reward":135660000,"staked":"5199644867","buffer":"373383392","tokens":[{"hash":"zil1hpwshtxspjakjh5sn7vn4e7pp4gaqkefup24h2","decimals":4,"volume":"54402192","symbol":"XPORT"},{"hash":"zil14pzuzq6v6pmmmrfjhczywguu0e97djepxt8g3e","decimals":15,"volume":"75992986286757407259","symbol":"gZIL"},{"hash":"zil1p5suryq6q647usxczale29cu3336hhp376c627","decimals":12,"volume":"19968963473964834","symbol":"ZWAP"},{"hash":"zil1dccsly0lwkkxhxxazldcnph05v2dz8maz46g05","decimals":4,"volume":"1408461","symbol":"RWD"},{"hash":"zil18f5rlhqz9vndw4w8p60d0n7vg3n9sqvta7n6t2","decimals":4,"volume":"661473213","symbol":"PORT"},{"hash":"zil1h63h5rlg7avatnlzhfnfzwn8vfspwkapzdy2aw","decimals":6,"volume":"3600356657","symbol":"XCAD"},{"hash":"zil1ucvrn22x8366vzpw5t7su6eyml2auczu6wnqqg","decimals":8,"volume":"184148206738669","symbol":"ZYRO"},{"hash":"zil1qzwxvp3wz3q5ewzg3afesut9pqfax0sjdyna42","decimals":2,"volume":"4017223","symbol":"MESSI"},{"hash":"zil1kwfu3x9n6fsuxc4ynp72uk5rxge25enw7zsf9z","decimals":4,"volume":"6904008441","symbol":"SCO"},{"hash":"zil1ykcdhtgyercmv7ndfxt00wm9xzpq4k7hjmfm4e","decimals":12,"volume":"39190578223011349","symbol":"MAMBO"},{"hash":"zil1lq3ghn3yaqk0w7fqtszv53hejunpyfyh3rx9gc","decimals":3,"volume":"5665","symbol":"Elons"},{"hash":"zil180v66mlw007ltdv8tq5t240y7upwgf7djklmwh","decimals":6,"volume":"1032294709331","symbol":"XSGD"},{"hash":"zil1hau7z6rjltvjc95pphwj57umdpvv0d6kh2t8zk","decimals":8,"volume":"15204475833378","symbol":"CARB"},{"hash":"zil1pqcev4ykxla0jhy3anx32lnqgv8xncd8q57ql2","decimals":4,"volume":"2962941110","symbol":"SPW"},{"hash":"zil14jmjrkvfcz2uvj3y69kl6gas34ecuf2j5ggmye","decimals":9,"volume":"9392300674329","symbol":"REDC"},{"hash":"zil1504065pp76uuxm7s9m2c4gwszhez8pu3mp6r8c","decimals":8,"volume":"17758936921784","symbol":"STREAM"},{"hash":"zil1s8xzysqcxva2x6aducncv9um3zxr36way3fx9g","decimals":6,"volume":"11481381748","symbol":"ZCH"},{"hash":"zil1qldr63ds7yuspqcf02263y2lctmtqmr039vrht","decimals":4,"volume":"105776473098","symbol":"ZPAINT"},{"hash":"zil1w5hwupgc9rxyuyd742g2c9annwahugrx80fw9h","decimals":4,"volume":"127504","symbol":"GARY"},{"hash":"zil1c6akv8k6dqaac7ft8ezk5gr2jtxrewfw8hc27d","decimals":2,"volume":"60","symbol":"DUCK"},{"hash":"zil1xswavlggsqmkd9kddcp0ulceqm9ht36gqkt8ua","decimals":12,"volume":"8502038049949674","symbol":"ZWALL"},{"hash":"zil14d6wwelssqumu6w9c6kaucz2r57z34cxuh96lf","decimals":12,"volume":"25381165922501667","symbol":"SHARDS"},{"hash":"zil168qdlq4xsua6ac9hugzntqyasf8gs7aund882v","decimals":2,"volume":"24051","symbol":"SRV"},{"hash":"zil148824ht7uxe67ltv4993wsdanr43hctrxjt5jz","decimals":null,"volume":"1178","symbol":"The world's most inexpensive resource for novels, textbooks, scholarly articles & other publications"},{"hash":"zil1l0g8u6f9g0fsvjuu74ctyla2hltefrdyt7k5f4","decimals":18,"volume":"22437380998539240746670","symbol":"ZLP"},{"hash":"zil1r9dcsrya4ynuxnzaznu00e6hh3kpt7vhvzgva0","decimals":5,"volume":"32037142","symbol":"ZLF"},{"hash":"zil1knvrhm9e2rqfdvqp50gu02a3pat34e6lst9d36","decimals":null,"volume":"13247","symbol":"DZT"},{"hash":"zil1sgdw5xgcpvyx3u3rqy287rpgyppg85t8dwyydr","decimals":null,"volume":"63449","symbol":"UFFSNFT"},{"hash":"zil17tsmlqgnzlfxsq4evm6n26txm2xlp5hele0kew","decimals":6,"volume":"230736967","symbol":"SHRK"},{"hash":"zil1k7qe4y7tgj0h0zv3z65xvukhm7mtqrkuqrrjh4","decimals":null,"volume":"28","symbol":"10 Beautiful Creatures from my World!"},{"hash":"zil1vsxlvznhtxtlpuhs948gpzylgsmyufqmw2j32f","decimals":4,"volume":"309247","symbol":"APE"}],"networkVolumeRune":null,"networkVolumeUSD":null},{"timestamp":1627776000000,"creationCount":1825,"tokenCreationCount":288,"txCount":1281309,"growthCount":150232,"reward":146268000,"staked":"5141253409","buffer":"365087718","tokens":[{"hash":"zil1hpwshtxspjakjh5sn7vn4e7pp4gaqkefup24h2","decimals":4,"volume":"225051163","symbol":"XPORT"},{"hash":"zil14pzuzq6v6pmmmrfjhczywguu0e97djepxt8g3e","decimals":15,"volume":"107977834462670215868","symbol":"gZIL"},{"hash":"zil1p5suryq6q647usxczale29cu3336hhp376c627","decimals":12,"volume":"58645408947791426","symbol":"ZWAP"},{"hash":"zil1qldr63ds7yuspqcf02263y2lctmtqmr039vrht","decimals":4,"volume":"13039395854","symbol":"ZPAINT"},{"hash":"zil18f5rlhqz9vndw4w8p60d0n7vg3n9sqvta7n6t2","decimals":4,"volume":"208996157","symbol":"PORT"},{"hash":"zil14jmjrkvfcz2uvj3y69kl6gas34ecuf2j5ggmye","decimals":9,"volume":"149824537035","symbol":"REDC"},{"hash":"zil180v66mlw007ltdv8tq5t240y7upwgf7djklmwh","decimals":6,"volume":"2413275883898","symbol":"XSGD"},{"hash":"zil168qdlq4xsua6ac9hugzntqyasf8gs7aund882v","decimals":2,"volume":"69642","symbol":"SRV"},{"hash":"zil1s8xzysqcxva2x6aducncv9um3zxr36way3fx9g","decimals":6,"volume":"50698746421","symbol":"ZCH"},{"hash":"zil1kwfu3x9n6fsuxc4ynp72uk5rxge25enw7zsf9z","decimals":4,"volume":"6494903493","symbol":"SCO"},{"hash":"zil1504065pp76uuxm7s9m2c4gwszhez8pu3mp6r8c","decimals":8,"volume":"7115191669464","symbol":"STREAM"},{"hash":"zil1hau7z6rjltvjc95pphwj57umdpvv0d6kh2t8zk","decimals":8,"volume":"13657993015383","symbol":"CARB"},{"hash":"zil1pqcev4ykxla0jhy3anx32lnqgv8xncd8q57ql2","decimals":4,"volume":"12660843100","symbol":"SPW"},{"hash":"zil1ucvrn22x8366vzpw5t7su6eyml2auczu6wnqqg","decimals":8,"volume":"533120451673776","symbol":"ZYRO"},{"hash":"zil1vq466xp683vjstgqyy7lwn0d7mc4e4gadhtr9k","decimals":null,"volume":"6","symbol":"DDX"},{"hash":"zil1yapyfmkhzxmgyeg5pkqmxjxxhuut4j9hpfy97l","decimals":0,"volume":"1536","symbol":"BUTT"},{"hash":"zil1w5hwupgc9rxyuyd742g2c9annwahugrx80fw9h","decimals":4,"volume":"26355","symbol":"GARY"},{"hash":"zil17hdu9r4h49d7gyh8s7zkeh3yatqft62uvsu8ep","decimals":4,"volume":"20924","symbol":"DogZilliqa"},{"hash":"zil1gf5vxndx44q6fn025fwdaajnrmgvngdzel0jzp","decimals":2,"volume":"101035316","symbol":"BLOX"},{"hash":"zil1c6akv8k6dqaac7ft8ezk5gr2jtxrewfw8hc27d","decimals":2,"volume":"1123","symbol":"DUCK"},{"hash":"zil14d6wwelssqumu6w9c6kaucz2r57z34cxuh96lf","decimals":12,"volume":"939265535257042","symbol":"SHARDS"},{"hash":"zil1xaljjgut7nvdkf95nl09jsa5x8cmjxh9aa0nxq","decimals":null,"volume":"1","symbol":"An amateur artist trying to find his own way."},{"hash":"zil1h63h5rlg7avatnlzhfnfzwn8vfspwkapzdy2aw","decimals":6,"volume":"1883490438","symbol":"XCAD"},{"hash":"zil1ykcdhtgyercmv7ndfxt00wm9xzpq4k7hjmfm4e","decimals":12,"volume":"162062626774848","symbol":"MAMBO"},{"hash":"zil1r9dcsrya4ynuxnzaznu00e6hh3kpt7vhvzgva0","decimals":5,"volume":"273849858","symbol":"ZLF"},{"hash":"zil1xswavlggsqmkd9kddcp0ulceqm9ht36gqkt8ua","decimals":12,"volume":"3192318875278571","symbol":"ZWALL"},{"hash":"zil1knvrhm9e2rqfdvqp50gu02a3pat34e6lst9d36","decimals":null,"volume":"14169","symbol":"DZT"},{"hash":"zil12rpq9shyvrd2rzrcyx2jn5t74y9g5c2xn095qe","decimals":6,"volume":"3370077663","symbol":"EGGZ"},{"hash":"zil1vdc79fg75sth96xnt6xmq5f55swcd5t6m5zhvn","decimals":5,"volume":"5588633","symbol":"Yoda"}],"networkVolumeRune":null,"networkVolumeUSD":null},{"timestamp":1630368000000,"creationCount":2055,"tokenCreationCount":746,"txCount":1473936,"growthCount":150693,"reward":153612000,"staked":"4913304332","buffer":"282411522","tokens":[{"hash":"zil1ucvrn22x8366vzpw5t7su6eyml2auczu6wnqqg","decimals":8,"volume":"91877332417396","symbol":"ZYRO"},{"hash":"zil14pzuzq6v6pmmmrfjhczywguu0e97djepxt8g3e","decimals":15,"volume":"134459521182490024642","symbol":"gZIL"},{"hash":"zil1p5suryq6q647usxczale29cu3336hhp376c627","decimals":12,"volume":"50525555685845920","symbol":"ZWAP"},{"hash":"zil14d6wwelssqumu6w9c6kaucz2r57z34cxuh96lf","decimals":12,"volume":"408354522558222","symbol":"SHARDS"},{"hash":"zil1hpwshtxspjakjh5sn7vn4e7pp4gaqkefup24h2","decimals":4,"volume":"27210000","symbol":"XPORT"},{"hash":"zil1sgdw5xgcpvyx3u3rqy287rpgyppg85t8dwyydr","decimals":null,"volume":"110153","symbol":"UFFSNFT"},{"hash":"zil1vdc79fg75sth96xnt6xmq5f55swcd5t6m5zhvn","decimals":5,"volume":"24279735","symbol":"Yoda"},{"hash":"zil1hau7z6rjltvjc95pphwj57umdpvv0d6kh2t8zk","decimals":8,"volume":"2210795947661","symbol":"CARB"},{"hash":"zil180v66mlw007ltdv8tq5t240y7upwgf7djklmwh","decimals":6,"volume":"4129551963378","symbol":"XSGD"},{"hash":"zil13vwxw6lu0uj8vgrhg3ua5h9n0zexd4utsakc29","decimals":null,"volume":"14","symbol":"Test Store 2"},{"hash":"zil1gf5vxndx44q6fn025fwdaajnrmgvngdzel0jzp","decimals":2,"volume":"52600476","symbol":"BLOX"},{"hash":"zil1ke24adh3gglmrp5h5tph7udh7luhy28z4pcly9","decimals":null,"volume":"18","symbol":"playmobil figure"},{"hash":"zil1h63h5rlg7avatnlzhfnfzwn8vfspwkapzdy2aw","decimals":6,"volume":"81790927250","symbol":"XCAD"},{"hash":"zil18f5rlhqz9vndw4w8p60d0n7vg3n9sqvta7n6t2","decimals":4,"volume":"2389790868","symbol":"PORT"},{"hash":"zil1rcp57nc2ue00f2hk7esxaa3j8q93xrexgrmpz7","decimals":12,"volume":"27128622276932","symbol":"ZILLEX"},{"hash":"zil19cyp6kj7zrz3c2q50ts2nly6hrhrr7vr89g9gf","decimals":2,"volume":"33998","symbol":"UNIDEX"},{"hash":"zil17hdu9r4h49d7gyh8s7zkeh3yatqft62uvsu8ep","decimals":4,"volume":"18102","symbol":"DogZilliqa"},{"hash":"zil1r9dcsrya4ynuxnzaznu00e6hh3kpt7vhvzgva0","decimals":5,"volume":"6619819","symbol":"ZLF"},{"hash":"zil1pqcev4ykxla0jhy3anx32lnqgv8xncd8q57ql2","decimals":4,"volume":"7489090646","symbol":"SPW"},{"hash":"zil1ykcdhtgyercmv7ndfxt00wm9xzpq4k7hjmfm4e","decimals":12,"volume":"744630727953865505","symbol":"MAMBO"},{"hash":"zil1kwfu3x9n6fsuxc4ynp72uk5rxge25enw7zsf9z","decimals":4,"volume":"1756604346","symbol":"SCO"},{"hash":"zil19lr3vlpm4lufu2q94mmjvdkvmx8wdwajuntzx2","decimals":18,"volume":"699296226888890346075104","symbol":"DMZ"},{"hash":"zil1d6qzuaymt5elr5xl7c0uen06kqflmglgj2aq3g","decimals":null,"volume":"8","symbol":"ZilBeachGirl - Access Pass"},{"hash":"zil12drvflckms6874ffuujcdxj75raavl4yfn4ssc","decimals":12,"volume":"26253300984989634","symbol":"RECAP"},{"hash":"zil1xswavlggsqmkd9kddcp0ulceqm9ht36gqkt8ua","decimals":12,"volume":"14885162060801923","symbol":"ZWALL"},{"hash":"zil108ex3na3dvwnjq5p4nls4z3gjy8fx66693hf4d","decimals":6,"volume":"86302595123","symbol":"CONSULT"},{"hash":"zil1w5hwupgc9rxyuyd742g2c9annwahugrx80fw9h","decimals":4,"volume":"3000","symbol":"GARY"},{"hash":"zil12htx8pdfwk39e47fhd7t3vd3rftyxeuf9px354","decimals":5,"volume":"370970890749","symbol":"PELE"},{"hash":"zil168qdlq4xsua6ac9hugzntqyasf8gs7aund882v","decimals":2,"volume":"225980","symbol":"SRV"},{"hash":"zil1c6akv8k6dqaac7ft8ezk5gr2jtxrewfw8hc27d","decimals":2,"volume":"467","symbol":"DUCK"},{"hash":"zil1qzwxvp3wz3q5ewzg3afesut9pqfax0sjdyna42","decimals":2,"volume":"100332","symbol":"MESSI"},{"hash":"zil1504065pp76uuxm7s9m2c4gwszhez8pu3mp6r8c","decimals":8,"volume":"8525710760413","symbol":"STREAM"},{"hash":"zil1aqu3cqd0nrlyvp3hms5gzqvpueedd2e806e9rs","decimals":4,"volume":"500000","symbol":"SIMP"},{"hash":"zil1auqyk36cdf3y8plujjfu958xturt6l3ehandqz","decimals":null,"volume":"131","symbol":""},{"hash":"zil1knvrhm9e2rqfdvqp50gu02a3pat34e6lst9d36","decimals":null,"volume":"479686","symbol":"DZT"},{"hash":"zil1anvrk3hs66fnepzkzzf89dafa0yzl43cu2a74w","decimals":null,"volume":"297","symbol":""},{"hash":"zil1l0g8u6f9g0fsvjuu74ctyla2hltefrdyt7k5f4","decimals":18,"volume":"29559047444342096706311","symbol":"ZLP"},{"hash":"zil167flx79fykulp57ykmh9gnf3curcnyux6dcj5e","decimals":null,"volume":"4729394","symbol":"BEAR"},{"hash":"zil1s8xzysqcxva2x6aducncv9um3zxr36way3fx9g","decimals":6,"volume":"1503248515","symbol":"ZCH"},{"hash":"zil18l7eyut8t4gu68w7mg0ck664ee33mykrycps6l","decimals":0,"volume":"29","symbol":"NFTDEX"},{"hash":"zil1z4hxwnqk9gu6tamcw4umxss9wjpmrkhzdh4n85","decimals":6,"volume":"700000000","symbol":"FRANC"},{"hash":"zil15ax5r66lducw7rycd73geytz97ktysftrj4k6p","decimals":null,"volume":"6","symbol":"Sweaty Nfts"},{"hash":"zil1lzkx6w9z2t8gga3s94s6tvkz0wer9lr2cs56qc","decimals":null,"volume":"15","symbol":"SAZ"},{"hash":"zil1ncm8f6p2jy0axfsxppr08yf5k42ermjegpv39u","decimals":null,"volume":"7","symbol":"9999FS"},{"hash":"zil1exsd8d3e250gcvpffd8a38lyhxy4zexxnvvpjr","decimals":null,"volume":"20","symbol":"ZAMONGUS"},{"hash":"zil1zl2etvuhuk2r4qygn36nvtq24mlxnf44z2h08d","decimals":12,"volume":"0","symbol":"NEWS"},{"hash":"zil14jmjrkvfcz2uvj3y69kl6gas34ecuf2j5ggmye","decimals":9,"volume":"1009580551370","symbol":"REDC"},{"hash":"zil1fjca5gwnqed48c6q0nqfn700rg3h2c4c57e0th","decimals":9,"volume":"654869521984","symbol":"TRUSTME"},{"hash":"zil18rkzgfcf0szt0qm8v75yv2ksr9p5qcwkcn54d6","decimals":null,"volume":"405","symbol":"Fun and Spooky NFT's"},{"hash":"zil1mxfe5ag2jfq4mk7509nutj8jj9e22xyyct0c6e","decimals":null,"volume":"299","symbol":"Cryptyotes"},{"hash":"zil1m6qrk9mkmhnrd0267yfrwmf4mgcgg8apsdw55a","decimals":null,"volume":"41","symbol":"A-M-P"},{"hash":"zil1lq3ghn3yaqk0w7fqtszv53hejunpyfyh3rx9gc","decimals":3,"volume":"2035","symbol":"Elons"},{"hash":"zil1kcwq4m3998c3ss96qlmklu364mdgh6t33w5vvp","decimals":null,"volume":"18","symbol":"ANIME"},{"hash":"zil1t6mx7wm5qfvffu6c69vng3cew3536c6k64nucx","decimals":null,"volume":"898","symbol":""},{"hash":"zil1nhuzjg452rkdzrfh7swllr4eq2g8t0lfgu2z38","decimals":8,"volume":"231939151282","symbol":"PLANET"},{"hash":"zil14kvsvrjp6ndwf0xmlt0z5yqva2h9za6fyuwmur","decimals":null,"volume":"4","symbol":"SAM"},{"hash":"zil1rrtmdqwms2a58gpzsk5ndfc5lmkttj4360vl2z","decimals":null,"volume":"1146","symbol":"DZIL"}],"networkVolumeRune":null,"networkVolumeUSD":null},{"timestamp":1632960000000,"creationCount":1171,"tokenCreationCount":292,"txCount":1481332,"growthCount":167006,"reward":155448000,"staked":"4923237360","buffer":"693208314","tokens":[{"hash":"zil1hpwshtxspjakjh5sn7vn4e7pp4gaqkefup24h2","decimals":4,"volume":"43874172","symbol":"XPORT"},{"hash":"zil1kwfu3x9n6fsuxc4ynp72uk5rxge25enw7zsf9z","decimals":4,"volume":"4523177020","symbol":"SCO"},{"hash":"zil14pzuzq6v6pmmmrfjhczywguu0e97djepxt8g3e","decimals":15,"volume":"76639844866538697009","symbol":"gZIL"},{"hash":"zil12htx8pdfwk39e47fhd7t3vd3rftyxeuf9px354","decimals":5,"volume":"35561032652","symbol":"PELE"},{"hash":"zil1p5suryq6q647usxczale29cu3336hhp376c627","decimals":12,"volume":"31369102577430262","symbol":"ZWAP"},{"hash":"zil180v66mlw007ltdv8tq5t240y7upwgf7djklmwh","decimals":6,"volume":"2923543425370","symbol":"XSGD"},{"hash":"zil19j33tapjje2xzng7svslnsjjjgge930jx0w09v","decimals":18,"volume":"562766569587842177166","symbol":"zETH"},{"hash":"zil1hau7z6rjltvjc95pphwj57umdpvv0d6kh2t8zk","decimals":8,"volume":"4664750562962","symbol":"CARB"},{"hash":"zil1sxx29cshups269ahh5qjffyr58mxjv9ft78jqy","decimals":6,"volume":"5046592512640","symbol":"zUSDT"},{"hash":"zil1zl2etvuhuk2r4qygn36nvtq24mlxnf44z2h08d","decimals":12,"volume":"0","symbol":"NEWS"},{"hash":"zil1epq9dyctg0m5yaxeqv7ph0j532qze28psqfu8h","decimals":12,"volume":"240116624555625903","symbol":"BUTTON"},{"hash":"zil1ucvrn22x8366vzpw5t7su6eyml2auczu6wnqqg","decimals":8,"volume":"278453808016761","symbol":"ZYRO"},{"hash":"zil18f5rlhqz9vndw4w8p60d0n7vg3n9sqvta7n6t2","decimals":4,"volume":"481827217","symbol":"PORT"},{"hash":"zil1m6qrk9mkmhnrd0267yfrwmf4mgcgg8apsdw55a","decimals":null,"volume":"68","symbol":"A-M-P"},{"hash":"zil1s8xzysqcxva2x6aducncv9um3zxr36way3fx9g","decimals":6,"volume":"100000000","symbol":"ZCH"},{"hash":"zil1gf5vxndx44q6fn025fwdaajnrmgvngdzel0jzp","decimals":2,"volume":"5254156","symbol":"BLOX"},{"hash":"zil15xycxe26ly2p489ac8zym6zkt4zw953e6sl5zq","decimals":null,"volume":"151851","symbol":"OPEN"},{"hash":"zil1jy3g5j9w5njqwxuuv3zwkz9syyueelmu7g080v","decimals":4,"volume":"30401884905","symbol":"FEES"},{"hash":"zil1c6akv8k6dqaac7ft8ezk5gr2jtxrewfw8hc27d","decimals":2,"volume":"351","symbol":"DUCK"},{"hash":"zil19lr3vlpm4lufu2q94mmjvdkvmx8wdwajuntzx2","decimals":18,"volume":"59129325945767949682943","symbol":"DMZ"},{"hash":"zil1ttspeq0z6qy7hglnkltymerp3zjcaqupk3wce7","decimals":null,"volume":"137924","symbol":"WAIFU"},{"hash":"zil1wha8mzaxhm22dpm5cav2tepuldnr8kwkvmqtjq","decimals":8,"volume":"1426939796","symbol":"zWBTC"},{"hash":"zil12drvflckms6874ffuujcdxj75raavl4yfn4ssc","decimals":12,"volume":"12117889922384","symbol":"RECAP"},{"hash":"zil168qdlq4xsua6ac9hugzntqyasf8gs7aund882v","decimals":2,"volume":"243975","symbol":"SRV"},{"hash":"zil1vdc79fg75sth96xnt6xmq5f55swcd5t6m5zhvn","decimals":5,"volume":"3084944","symbol":"Yoda"},{"hash":"zil108ex3na3dvwnjq5p4nls4z3gjy8fx66693hf4d","decimals":6,"volume":"1750000000","symbol":"CONSULT"},{"hash":"zil1xswavlggsqmkd9kddcp0ulceqm9ht36gqkt8ua","decimals":12,"volume":"29539062394087189","symbol":"ZWALL"},{"hash":"zil1h63h5rlg7avatnlzhfnfzwn8vfspwkapzdy2aw","decimals":6,"volume":"76630128947","symbol":"XCAD"},{"hash":"zil1504065pp76uuxm7s9m2c4gwszhez8pu3mp6r8c","decimals":8,"volume":"6276651066976","symbol":"STREAM"},{"hash":"zil12jhxfcsfyaylhrf9gu8lc82ddgvudu4tzvduum","decimals":5,"volume":"4565399123","symbol":"Oki"},{"hash":"zil1z99wjqd57rge9q08xmca6aktvg8sr3f7mpj5cv","decimals":3,"volume":"2858083414","symbol":"LUCKY"},{"hash":"zil1l0g8u6f9g0fsvjuu74ctyla2hltefrdyt7k5f4","decimals":18,"volume":"2646025237897998579716","symbol":"ZLP"},{"hash":"zil19cyp6kj7zrz3c2q50ts2nly6hrhrr7vr89g9gf","decimals":2,"volume":"320554","symbol":"UNIDEX"},{"hash":"zil1lq3ghn3yaqk0w7fqtszv53hejunpyfyh3rx9gc","decimals":3,"volume":"5850","symbol":"Elons"},{"hash":"zil1pqcev4ykxla0jhy3anx32lnqgv8xncd8q57ql2","decimals":4,"volume":"38323457280","symbol":"SPW"},{"hash":"zil1rcp57nc2ue00f2hk7esxaa3j8q93xrexgrmpz7","decimals":12,"volume":"50000000000000","symbol":"ZILLEX"},{"hash":"zil1gvr0jgwfsfmxsyx0xsnhtlte4gks6r3yk8x5fn","decimals":12,"volume":"326015311000000000","symbol":"wZIL"},{"hash":"zil1knvrhm9e2rqfdvqp50gu02a3pat34e6lst9d36","decimals":null,"volume":"24398","symbol":"DZT"},{"hash":"zil1anm4a42h308lz5gm7c5p6lyytr5h9fl5sk5ufc","decimals":null,"volume":"23","symbol":"ETHW"},{"hash":"zil1ykcdhtgyercmv7ndfxt00wm9xzpq4k7hjmfm4e","decimals":12,"volume":"143059829459570025","symbol":"MAMBO"},{"hash":"zil1sgdw5xgcpvyx3u3rqy287rpgyppg85t8dwyydr","decimals":null,"volume":"7484","symbol":"UFFSNFT"},{"hash":"zil1p75qj26gkj4z0ldnmn7e5ukw5lvc5853wxe0lg","decimals":null,"volume":"1696","symbol":"ICED"},{"hash":"zil1qzwxvp3wz3q5ewzg3afesut9pqfax0sjdyna42","decimals":2,"volume":"962103","symbol":"MESSI"},{"hash":"zil1094qz7m7mw3e7swxqnffkhapya6srrt6zrd4xy","decimals":9,"volume":"29888241338546","symbol":"lvr"},{"hash":"zil1xxl6yp2twxvljdnn87g9fk7wykdrcv66xdy4rc","decimals":4,"volume":"8339295280","symbol":"Lunr"},{"hash":"zil14jmjrkvfcz2uvj3y69kl6gas34ecuf2j5ggmye","decimals":9,"volume":"107965083026","symbol":"REDC"},{"hash":"zil18u8uscxs8pjdkzccfy8dtnh2x0lfze5gkav5ft","decimals":null,"volume":"101","symbol":"Magical Floof for All!"},{"hash":"zil15uqy4c6sagcfgd0gyvy8274eggpknwnzlnaest","decimals":null,"volume":"128650","symbol":"APE"},{"hash":"zil1cs2au702hcx779yxdg49txjqe7rn989rty3wwy","decimals":6,"volume":"38400870696","symbol":"ADS"},{"hash":"zil1w5hwupgc9rxyuyd742g2c9annwahugrx80fw9h","decimals":4,"volume":"230","symbol":"GARY"},{"hash":"zil1jf6lp5ff0hdy96at2v3am634cy3ls9g8ex36xn","decimals":null,"volume":"58","symbol":"You can find here some art, illustration, social banner, avatar, mockup, logo, template with high quality"},{"hash":"zil167flx79fykulp57ykmh9gnf3curcnyux6dcj5e","decimals":null,"volume":"6492","symbol":"BEAR"},{"hash":"zil1gcdkmkuunj0l6hjl48zzye50g397dgslzdf4uk","decimals":null,"volume":"2113","symbol":"OAC"},{"hash":"zil17q6j7m6zzrn8yclvayhq060a4swtt0hchytt2x","decimals":6,"volume":"143343000000","symbol":"Inuzil"},{"hash":"zil1xnn9lspfx696x5yw3jcvuzfnnqpxsnfzq0pzdp","decimals":null,"volume":"24","symbol":"ICED"},{"hash":"zil1a7pp23ae5ad72ckpsq2ghg886tvmuln35qj2tf","decimals":null,"volume":"1932","symbol":"collection of 1000 nft 1/1"}],"networkVolumeRune":null,"networkVolumeUSD":null},{"timestamp":1635552000000,"creationCount":3377,"tokenCreationCount":267,"txCount":1696910,"growthCount":199312,"reward":154632000,"staked":"4657389198","buffer":"241101490","tokens":[{"hash":"zil1xxl6yp2twxvljdnn87g9fk7wykdrcv66xdy4rc","decimals":4,"volume":"15477051200","symbol":"Lunr"},{"hash":"zil167flx79fykulp57ykmh9gnf3curcnyux6dcj5e","decimals":null,"volume":"NaN","symbol":"BEAR"},{"hash":"zil14pzuzq6v6pmmmrfjhczywguu0e97djepxt8g3e","decimals":15,"volume":"12690665147780404598","symbol":"gZIL"},{"hash":"zil12jhxfcsfyaylhrf9gu8lc82ddgvudu4tzvduum","decimals":5,"volume":"13571135489","symbol":"Oki"},{"hash":"zil15xycxe26ly2p489ac8zym6zkt4zw953e6sl5zq","decimals":null,"volume":"197866","symbol":"OPEN"},{"hash":"zil19lr3vlpm4lufu2q94mmjvdkvmx8wdwajuntzx2","decimals":18,"volume":"14532643399856337428574","symbol":"DMZ"},{"hash":"zil1hpwshtxspjakjh5sn7vn4e7pp4gaqkefup24h2","decimals":4,"volume":"63163741","symbol":"XPORT"},{"hash":"zil1gvr0jgwfsfmxsyx0xsnhtlte4gks6r3yk8x5fn","decimals":12,"volume":"345086149999999990","symbol":"wZIL"},{"hash":"zil1h8a9tzel4hjz44gtpl384758crzfln4fptya7j","decimals":null,"volume":"17","symbol":"SNEKS"},{"hash":"zil19j33tapjje2xzng7svslnsjjjgge930jx0w09v","decimals":18,"volume":"520964148056144201207","symbol":"zETH"},{"hash":"zil1pqcev4ykxla0jhy3anx32lnqgv8xncd8q57ql2","decimals":4,"volume":"30022369075","symbol":"SPW"},{"hash":"zil1p8gy36xg6s93fldy6nc978uk9camm6kqz75eea","decimals":null,"volume":"5","symbol":"Unique NFT Collectibles"},{"hash":"zil1sxx29cshups269ahh5qjffyr58mxjv9ft78jqy","decimals":6,"volume":"5631287476771","symbol":"zUSDT"},{"hash":"zil1p5suryq6q647usxczale29cu3336hhp376c627","decimals":12,"volume":"9083431798857274","symbol":"ZWAP"},{"hash":"zil1wha8mzaxhm22dpm5cav2tepuldnr8kwkvmqtjq","decimals":8,"volume":"3149221832","symbol":"zWBTC"},{"hash":"zil18f5rlhqz9vndw4w8p60d0n7vg3n9sqvta7n6t2","decimals":4,"volume":"1689192255","symbol":"PORT"},{"hash":"zil1zl2etvuhuk2r4qygn36nvtq24mlxnf44z2h08d","decimals":12,"volume":"0","symbol":"NEWS"},{"hash":"zil14d6wwelssqumu6w9c6kaucz2r57z34cxuh96lf","decimals":12,"volume":"268680494666954","symbol":"SHARDS"},{"hash":"zil1gf5vxndx44q6fn025fwdaajnrmgvngdzel0jzp","decimals":2,"volume":"7823863","symbol":"BLOX"},{"hash":"zil1fgqmhj9rleprcy67y5mjzj78rxk4ttj4q89y0l","decimals":null,"volume":"128","symbol":"RAF03"},{"hash":"zil1c6akv8k6dqaac7ft8ezk5gr2jtxrewfw8hc27d","decimals":2,"volume":"243","symbol":"DUCK"},{"hash":"zil1knvrhm9e2rqfdvqp50gu02a3pat34e6lst9d36","decimals":null,"volume":"137656","symbol":"DZT"},{"hash":"zil1hau7z6rjltvjc95pphwj57umdpvv0d6kh2t8zk","decimals":8,"volume":"11880732534505","symbol":"CARB"},{"hash":"zil1s8xzysqcxva2x6aducncv9um3zxr36way3fx9g","decimals":6,"volume":"2961118588","symbol":"ZCH"},{"hash":"zil1usmdpndav207ash095txmmn7pkjj0023x2w48c","decimals":null,"volume":"266","symbol":"DZB"},{"hash":"zil1kwfu3x9n6fsuxc4ynp72uk5rxge25enw7zsf9z","decimals":4,"volume":"2145175567","symbol":"SCO"},{"hash":"zil1jy3g5j9w5njqwxuuv3zwkz9syyueelmu7g080v","decimals":4,"volume":"508154870","symbol":"FEES"},{"hash":"zil1z5l74hwy3pc3pr3gdh3nqju4jlyp0dzkhq2f5y","decimals":18,"volume":"724003009243486782211647","symbol":"XCAD"},{"hash":"zil1v5s3f9dds05et8mhtwlzh4l7klyrcnc679y27s","decimals":6,"volume":"12512238726","symbol":"PIL"},{"hash":"zil1ucvrn22x8366vzpw5t7su6eyml2auczu6wnqqg","decimals":8,"volume":"202876242771951","symbol":"ZYRO"},{"hash":"zil1h63h5rlg7avatnlzhfnfzwn8vfspwkapzdy2aw","decimals":6,"volume":"1628737532","symbol":"XCAD"},{"hash":"zil1ttspeq0z6qy7hglnkltymerp3zjcaqupk3wce7","decimals":null,"volume":"322","symbol":"WAIFU"},{"hash":"zil1sgdw5xgcpvyx3u3rqy287rpgyppg85t8dwyydr","decimals":null,"volume":"790048","symbol":"UFFSNFT"},{"hash":"zil1r9dcsrya4ynuxnzaznu00e6hh3kpt7vhvzgva0","decimals":5,"volume":"83110947","symbol":"ZLF"},{"hash":"zil1w5hwupgc9rxyuyd742g2c9annwahugrx80fw9h","decimals":4,"volume":"91683","symbol":"GARY"},{"hash":"zil1xswavlggsqmkd9kddcp0ulceqm9ht36gqkt8ua","decimals":12,"volume":"1269017308088402","symbol":"ZWALL"},{"hash":"zil180v66mlw007ltdv8tq5t240y7upwgf7djklmwh","decimals":6,"volume":"928527748513","symbol":"XSGD"},{"hash":"zil1epq9dyctg0m5yaxeqv7ph0j532qze28psqfu8h","decimals":12,"volume":"1482514646804492","symbol":"BUTTON"},{"hash":"zil1pwy2h0tpaf0g2nsa858vc7zrvdz6kdsx4gdzlk","decimals":null,"volume":"65","symbol":"Shroom"},{"hash":"zil1q0vq8xdsgw2vyxd6dvnhuu32tewtcu234r8vuz","decimals":null,"volume":"52","symbol":"The world of dreams in color"},{"hash":"zil1a7pp23ae5ad72ckpsq2ghg886tvmuln35qj2tf","decimals":null,"volume":"789","symbol":"collection of 1000 nft 1/1"},{"hash":"zil1vdfdvsl4r6c2uprfhzmpn4ypch9ukdxapjmnsa","decimals":null,"volume":"1","symbol":"Gary-1"},{"hash":"zil1pqgpfp9h797ymz5zju9hgegktslct67y6xkl40","decimals":null,"volume":"4","symbol":"ORG"},{"hash":"zil1nfuy0fuvdun80m6f5vxfqycz0caphpf8tksmlt","decimals":null,"volume":"1566","symbol":"DCF"},{"hash":"zil14jmjrkvfcz2uvj3y69kl6gas34ecuf2j5ggmye","decimals":9,"volume":"1308666196690","symbol":"REDC"},{"hash":"zil1l8l658hqwz6zmzr7e6emlnfshs9tg53qg3pju9","decimals":6,"volume":"30000000","symbol":"MILKY"},{"hash":"zil12drvflckms6874ffuujcdxj75raavl4yfn4ssc","decimals":12,"volume":"3027639585023000","symbol":"RECAP"},{"hash":"zil1anvrk3hs66fnepzkzzf89dafa0yzl43cu2a74w","decimals":null,"volume":"2279","symbol":""},{"hash":"zil1lq3ghn3yaqk0w7fqtszv53hejunpyfyh3rx9gc","decimals":3,"volume":"12450","symbol":"Elons"},{"hash":"zil14ap896p777m9jxst0pjx3ylctmcfjkw7zpq0t8","decimals":null,"volume":"1755","symbol":""},{"hash":"zil1kpfcq5vz7sey35j0ceut8sph4ft6vl00dxj4t7","decimals":null,"volume":"92","symbol":"ZAP"},{"hash":"zil1z0eeqa7t673gv94v83sdrk9fyffuayuxpkscna","decimals":null,"volume":"22739","symbol":"GODZ"},{"hash":"zil1ykcdhtgyercmv7ndfxt00wm9xzpq4k7hjmfm4e","decimals":12,"volume":"4408176850566556411","symbol":"MAMBO"},{"hash":"zil1qq5xx3jh26h2nnfynz5ljds0vpu8pp4n6c2xkk","decimals":null,"volume":"3262","symbol":"MONSTERS"},{"hash":"zil1frpsp3sm7u4fpql6sk48j8ngt4a8ektk067yv7","decimals":null,"volume":"27","symbol":"COLLECTION OF 100 NFT "},{"hash":"zil1ay6tggqqcjntdn65jpe7cqfjc2ndq46gsvukk3","decimals":null,"volume":"22","symbol":"FAC3"},{"hash":"zil1xr2qjdk85rlynqphvg70ttfdffp0p00n0vtclz","decimals":null,"volume":"44","symbol":"Zigns"},{"hash":"zil18puwmrvd9cmj2ypzaljjuxrafmftn3xtqc9ygs","decimals":null,"volume":"124","symbol":"111 Movie Legends - 2nd Collection"},{"hash":"zil1z3uasxxrktvlgwaj0c3u94x4ngnldf90mgusup","decimals":null,"volume":"1182","symbol":"FIRST GENERATION"},{"hash":"zil1tx6j5a2jtphd0e07ekd5w644vllmt7t20shp7s","decimals":null,"volume":"91","symbol":"Trading and Staking of Real World Asset NFT"},{"hash":"zil1l0g8u6f9g0fsvjuu74ctyla2hltefrdyt7k5f4","decimals":18,"volume":"407327460589515412250417","symbol":"ZLP"},{"hash":"zil1xnn9lspfx696x5yw3jcvuzfnnqpxsnfzq0pzdp","decimals":null,"volume":"63","symbol":"ICED"},{"hash":"zil1qzwxvp3wz3q5ewzg3afesut9pqfax0sjdyna42","decimals":2,"volume":"731611","symbol":"MESSI"},{"hash":"zil13t3r5k0thr3rqwezq0wuezeq8uuu0m6wgnztgj","decimals":null,"volume":"21","symbol":"URB3DSWEET"},{"hash":"zil1aqu3cqd0nrlyvp3hms5gzqvpueedd2e806e9rs","decimals":4,"volume":"10910000","symbol":"SIMP"},{"hash":"zil1vdc79fg75sth96xnt6xmq5f55swcd5t6m5zhvn","decimals":5,"volume":"962000","symbol":"Yoda"},{"hash":"zil1504065pp76uuxm7s9m2c4gwszhez8pu3mp6r8c","decimals":8,"volume":"620453942746","symbol":"STREAM"},{"hash":"zil1eg7dcyn8dxcgfshxmf9za2ljxju6kyq0vunszu","decimals":0,"volume":"34179","symbol":"GEMZ"},{"hash":"zil1k0s67azv52yx7lzcvh0gxxzfat7ydtva9gw0tz","decimals":null,"volume":"11339","symbol":"MUSK"},{"hash":"zil1qwkgpyvdzg4yg4gh878w65k8eqm2c0r0j3qnrx","decimals":null,"volume":"1573","symbol":"TPN"},{"hash":"zil1lzdur2r49c6v4egsap7w7cj289q0326z600r3z","decimals":null,"volume":"102","symbol":"Art"},{"hash":"zil1dngmc5x8mmknjhn3kwum6cs7e9cacex0hdfwfl","decimals":null,"volume":"6","symbol":"Watch&flow"},{"hash":"zil15aylzfjjkf6usjj7nxv0e8m855yz369jy2ymjx","decimals":null,"volume":"219","symbol":"Skullz"},{"hash":"zil1pwjgv88atmuy45e3ykxxckhmvkgzprw9q0kkwu","decimals":null,"volume":"1923","symbol":"Darkula"},{"hash":"zil1jl6zk3k4raeenwszk43adpyhk2frzk4tgnz7k8","decimals":null,"volume":"398","symbol":"Digital Art of all types."},{"hash":"zil1uydfxf7xw5xjmxs7jduwkgc2sgmm2astsfq7hc","decimals":null,"volume":"41","symbol":"BATZ"},{"hash":"zil1gt7u6vfc65rqtctk4q6xqygsmz03hlw8v989xs","decimals":null,"volume":"18","symbol":"LOCO"},{"hash":"zil1kmwnp6sl37fz3t4w2ssr00sy6x7pde5sf3h3gt","decimals":null,"volume":"27","symbol":"UFO"},{"hash":"zil1u8u769jnrt87agvknp0xrp2ue4gscgqrwp76mv","decimals":null,"volume":"2441","symbol":"COLLECTION OF 200 ZOMBIEPIX  EACH ZOMBIE IS A SINGLE 1/1 NFT  THE FIRST GENERATION OF ZOMBIES IS ALREADY HERE, JOIN ZOMBIEPIX AND WITNESS THE EVOLUTION OF CRYPTO ZOMBIE IN THE ZILLIQA BLOCK CHAIN"}],"networkVolumeRune":null,"networkVolumeUSD":null},{"timestamp":1638144000000,"creationCount":4362,"tokenCreationCount":201,"txCount":1536383,"growthCount":205671,"reward":155856000,"staked":"5583718918","buffer":"1252981114","tokens":[{"hash":"zil1xxl6yp2twxvljdnn87g9fk7wykdrcv66xdy4rc","decimals":4,"volume":"89522234576","symbol":"Lunr"},{"hash":"zil1hpwshtxspjakjh5sn7vn4e7pp4gaqkefup24h2","decimals":4,"volume":"2941056","symbol":"XPORT"},{"hash":"zil1jl6zk3k4raeenwszk43adpyhk2frzk4tgnz7k8","decimals":null,"volume":"1847","symbol":"Digital Art of all types."},{"hash":"zil1kwfu3x9n6fsuxc4ynp72uk5rxge25enw7zsf9z","decimals":4,"volume":"42364000153","symbol":"SCO"},{"hash":"zil180v66mlw007ltdv8tq5t240y7upwgf7djklmwh","decimals":6,"volume":"471918563826","symbol":"XSGD"},{"hash":"zil14pzuzq6v6pmmmrfjhczywguu0e97djepxt8g3e","decimals":15,"volume":"9686970846842914667","symbol":"gZIL"},{"hash":"zil1wha8mzaxhm22dpm5cav2tepuldnr8kwkvmqtjq","decimals":8,"volume":"77675457","symbol":"zWBTC"},{"hash":"zil1hau7z6rjltvjc95pphwj57umdpvv0d6kh2t8zk","decimals":8,"volume":"776191306815","symbol":"CARB"},{"hash":"zil19j33tapjje2xzng7svslnsjjjgge930jx0w09v","decimals":18,"volume":"56106591134976557052","symbol":"zETH"},{"hash":"zil1kmwnp6sl37fz3t4w2ssr00sy6x7pde5sf3h3gt","decimals":null,"volume":"25","symbol":"UFO"},{"hash":"zil18f5rlhqz9vndw4w8p60d0n7vg3n9sqvta7n6t2","decimals":4,"volume":"497154138","symbol":"PORT"},{"hash":"zil1p5suryq6q647usxczale29cu3336hhp376c627","decimals":12,"volume":"10710978589823718","symbol":"ZWAP"},{"hash":"zil1sxx29cshups269ahh5qjffyr58mxjv9ft78jqy","decimals":6,"volume":"764938130494","symbol":"zUSDT"},{"hash":"zil1z5l74hwy3pc3pr3gdh3nqju4jlyp0dzkhq2f5y","decimals":18,"volume":"392707842186463110900007","symbol":"XCAD"},{"hash":"zil1jy3g5j9w5njqwxuuv3zwkz9syyueelmu7g080v","decimals":4,"volume":"14443328670","symbol":"FEES"},{"hash":"zil1gf5vxndx44q6fn025fwdaajnrmgvngdzel0jzp","decimals":2,"volume":"14433057","symbol":"BLOX"},{"hash":"zil14jmjrkvfcz2uvj3y69kl6gas34ecuf2j5ggmye","decimals":9,"volume":"2529016510388","symbol":"REDC"},{"hash":"zil1eg7dcyn8dxcgfshxmf9za2ljxju6kyq0vunszu","decimals":0,"volume":"4662","symbol":"GEMZ"},{"hash":"zil1pqcev4ykxla0jhy3anx32lnqgv8xncd8q57ql2","decimals":4,"volume":"12968652556","symbol":"SPW"},{"hash":"zil1504065pp76uuxm7s9m2c4gwszhez8pu3mp6r8c","decimals":8,"volume":"2902757407232","symbol":"STREAM"},{"hash":"zil1qq5xx3jh26h2nnfynz5ljds0vpu8pp4n6c2xkk","decimals":null,"volume":"800","symbol":"MONSTERS"},{"hash":"zil1c6akv8k6dqaac7ft8ezk5gr2jtxrewfw8hc27d","decimals":2,"volume":"108","symbol":"DUCK"},{"hash":"zil10jrz6xut0czvl7j38c9dgagn3qly6cs8xhxgeh","decimals":null,"volume":"105","symbol":"EoZ"},{"hash":"zil1knvrhm9e2rqfdvqp50gu02a3pat34e6lst9d36","decimals":null,"volume":"4808","symbol":"DZT"},{"hash":"zil1dpj3xj7mryncq6fyqrcdlgx5txlnnhafpq382l","decimals":null,"volume":"774","symbol":"MNM"},{"hash":"zil1x6z064fkssmef222gkhz3u5fhx57kyssn7vlu0","decimals":18,"volume":"1076142492170438649697","symbol":"BOLT"},{"hash":"zil1pqgpfp9h797ymz5zju9hgegktslct67y6xkl40","decimals":null,"volume":"5","symbol":"ORG"},{"hash":"zil17uags0eppjfe74lst4pkl3weynlllzy594v2p2","decimals":null,"volume":"311","symbol":"Mystical"},{"hash":"zil133qfql0r3k33j8te8kpaxagdemupfd9wvh88ka","decimals":6,"volume":"600070077646","symbol":"ZAME"},{"hash":"zil1ucvrn22x8366vzpw5t7su6eyml2auczu6wnqqg","decimals":8,"volume":"8600000000","symbol":"ZYRO"},{"hash":"zil1rdu5xjtynxswc7hpeprkezvkt3z8dxv0stjlqr","decimals":null,"volume":"21","symbol":"Zcats"},{"hash":"zil1l0g8u6f9g0fsvjuu74ctyla2hltefrdyt7k5f4","decimals":18,"volume":"4719764229142512962763","symbol":"ZLP"},{"hash":"zil1w3rj8d0vqad3ms6m938cehyne3xe0s4s7t0e8m","decimals":null,"volume":"148","symbol":""},{"hash":"zil1pwjgv88atmuy45e3ykxxckhmvkgzprw9q0kkwu","decimals":null,"volume":"2859","symbol":"Darkula"},{"hash":"zil1la546rxzupwmyftuxrxv0fgaj75gjlgu6gymc8","decimals":null,"volume":"3968","symbol":"RoboUniCats"},{"hash":"zil16d7rhwezw3v7ua7sc0yekpm9u7fem76j87d7ev","decimals":null,"volume":"1827","symbol":"Dbz"},{"hash":"zil10dmr7sesrv2vxarqckq56ls0xktkjdkwrhz7wd","decimals":null,"volume":"6","symbol":"XX"},{"hash":"zil12htx8pdfwk39e47fhd7t3vd3rftyxeuf9px354","decimals":5,"volume":"21413580275","symbol":"PELE"},{"hash":"zil1vdc79fg75sth96xnt6xmq5f55swcd5t6m5zhvn","decimals":5,"volume":"500000","symbol":"Yoda"},{"hash":"zil1cuf78e3p37utekgk0gtcvd3hvkrqcgt06lrnty","decimals":6,"volume":"1601947961255070","symbol":"XIDR"},{"hash":"zil12jhxfcsfyaylhrf9gu8lc82ddgvudu4tzvduum","decimals":5,"volume":"162633516","symbol":"Oki"},{"hash":"zil1r32n9p5u5k99u5nl5tjvndyy0mjpcdvswzmu7w","decimals":4,"volume":"10000","symbol":"Tesla"},{"hash":"zil1p4mfm0pc29mlwdyjttugh50rqlzfwm4tuzu6nt","decimals":null,"volume":"2","symbol":"DRC"},{"hash":"zil1xtjd70x5dscgv2c2xrxmrpcytvg7ap6nl82px4","decimals":null,"volume":"6280212","symbol":"ULTIMATESPORTSNFT"},{"hash":"zil1m69wa3e4f762usju4m8wx52dc4tjvmkuvjsjdl","decimals":8,"volume":"12055464664336","symbol":"SWTH"},{"hash":"zil1yk93f957fanapf0yszgm84p62xrxxfytj4d2tl","decimals":8,"volume":"488042212978976","symbol":"SWTH"},{"hash":"zil1lcw5kucltv6dk6fkcv3wqukl89ee45utlhhpak","decimals":null,"volume":"146","symbol":"ZFam"},{"hash":"zil1t4hgmmeqque5l08dcy9teheuq0zxy08k4yjujd","decimals":null,"volume":"318","symbol":"$LMBZ"},{"hash":"zil19lr3vlpm4lufu2q94mmjvdkvmx8wdwajuntzx2","decimals":18,"volume":"77559576622059967936151","symbol":"DMZ"},{"hash":"zil1dnyu7c8par8p8vjdsa28fymh3znq2tfzja9m8d","decimals":null,"volume":"2","symbol":""},{"hash":"zil1q5tfyf7xdx2mfa7nhsa0hfyegppasfynxuqwyj","decimals":null,"volume":"69","symbol":"DrBbuzz"},{"hash":"zil1qldr63ds7yuspqcf02263y2lctmtqmr039vrht","decimals":4,"volume":"10328216","symbol":"ZPAINT"},{"hash":"zil14d6wwelssqumu6w9c6kaucz2r57z34cxuh96lf","decimals":12,"volume":"7427449490021133","symbol":"SHARDS"}],"networkVolumeRune":null,"networkVolumeUSD":null},{"timestamp":1640736000000,"creationCount":1156,"tokenCreationCount":57,"txCount":544832,"growthCount":61158,"reward":47736000,"staked":"5634262277","buffer":"137357481","tokens":[{"hash":"zil1xxl6yp2twxvljdnn87g9fk7wykdrcv66xdy4rc","decimals":4,"volume":"13860147954","symbol":"Lunr"},{"hash":"zil1p5suryq6q647usxczale29cu3336hhp376c627","decimals":12,"volume":"7134157228207839","symbol":"ZWAP"},{"hash":"zil19lr3vlpm4lufu2q94mmjvdkvmx8wdwajuntzx2","decimals":18,"volume":"14521665040417198444918","symbol":"DMZ"},{"hash":"zil1z5l74hwy3pc3pr3gdh3nqju4jlyp0dzkhq2f5y","decimals":18,"volume":"2394656661905150243005126","symbol":"XCAD"},{"hash":"zil19j33tapjje2xzng7svslnsjjjgge930jx0w09v","decimals":18,"volume":"38228742069889044409","symbol":"zETH"},{"hash":"zil14pzuzq6v6pmmmrfjhczywguu0e97djepxt8g3e","decimals":15,"volume":"2870412912307018750","symbol":"gZIL"},{"hash":"zil18f5rlhqz9vndw4w8p60d0n7vg3n9sqvta7n6t2","decimals":4,"volume":"483623019","symbol":"PORT"},{"hash":"zil1kwfu3x9n6fsuxc4ynp72uk5rxge25enw7zsf9z","decimals":4,"volume":"296566896","symbol":"SCO"},{"hash":"zil1sxx29cshups269ahh5qjffyr58mxjv9ft78jqy","decimals":6,"volume":"3031456927325","symbol":"zUSDT"},{"hash":"zil1s52qhnqgvw2g0m7ltltjwyp7y2j4jeh92dm2wy","decimals":null,"volume":"36","symbol":"SAC (Soul Ape Club)"},{"hash":"zil1yk93f957fanapf0yszgm84p62xrxxfytj4d2tl","decimals":8,"volume":"539324112752553","symbol":"SWTH"},{"hash":"zil1hau7z6rjltvjc95pphwj57umdpvv0d6kh2t8zk","decimals":8,"volume":"3236283866606","symbol":"CARB"},{"hash":"zil1eg7dcyn8dxcgfshxmf9za2ljxju6kyq0vunszu","decimals":0,"volume":"1271","symbol":"GEMZ"},{"hash":"zil1jy3g5j9w5njqwxuuv3zwkz9syyueelmu7g080v","decimals":4,"volume":"100442092866","symbol":"FEES"},{"hash":"zil1xfcg9hfpdlmz2aytz0s4dww35hfa6s0jnjut5f","decimals":18,"volume":"1036242997570932944621","symbol":"dXCAD"},{"hash":"zil180v66mlw007ltdv8tq5t240y7upwgf7djklmwh","decimals":6,"volume":"106255121123","symbol":"XSGD"},{"hash":"zil12jhxfcsfyaylhrf9gu8lc82ddgvudu4tzvduum","decimals":5,"volume":"1740501906","symbol":"Oki"},{"hash":"zil14jmjrkvfcz2uvj3y69kl6gas34ecuf2j5ggmye","decimals":9,"volume":"2958919634960","symbol":"REDC"},{"hash":"zil1c6akv8k6dqaac7ft8ezk5gr2jtxrewfw8hc27d","decimals":2,"volume":"167","symbol":"DUCK"},{"hash":"zil1anvrk3hs66fnepzkzzf89dafa0yzl43cu2a74w","decimals":null,"volume":"23","symbol":""},{"hash":"zil10zxwml0gh7qvskaytw2psy86k7qkh33l0hmx3q","decimals":null,"volume":"19","symbol":"worm"},{"hash":"zil1wha8mzaxhm22dpm5cav2tepuldnr8kwkvmqtjq","decimals":8,"volume":"24326366","symbol":"zWBTC"},{"hash":"zil1pqcev4ykxla0jhy3anx32lnqgv8xncd8q57ql2","decimals":4,"volume":"3333646020","symbol":"SPW"},{"hash":"zil1sgdw5xgcpvyx3u3rqy287rpgyppg85t8dwyydr","decimals":null,"volume":"53399","symbol":"UFFSNFT"},{"hash":"zil1cuf78e3p37utekgk0gtcvd3hvkrqcgt06lrnty","decimals":6,"volume":"28822381234750","symbol":"XIDR"},{"hash":"zil1gf5vxndx44q6fn025fwdaajnrmgvngdzel0jzp","decimals":2,"volume":"903199","symbol":"BLOX"},{"hash":"zil1ykcdhtgyercmv7ndfxt00wm9xzpq4k7hjmfm4e","decimals":12,"volume":"199441455715295311","symbol":"MAMBO"},{"hash":"zil14d6wwelssqumu6w9c6kaucz2r57z34cxuh96lf","decimals":12,"volume":"7427899741168","symbol":"SHARDS"},{"hash":"zil15efm3nscdqs62pmu7jdh3e03882exltlsre0a7","decimals":null,"volume":"93","symbol":"MS"},{"hash":"zil12htx8pdfwk39e47fhd7t3vd3rftyxeuf9px354","decimals":5,"volume":"8283728346","symbol":"PELE"}],"networkVolumeRune":null,"networkVolumeUSD":null}]}
